Workbook

Sheet Med
A1: Username | B1: Employee Id | C1: Designation | D1: Roles | E1: Units | F1: Department | G1: First Name | H1: Middle Name | I1: Last Name | J1: Phone | K1: Email Address | L1: Last Available At | M1: Enabled | N1: MultiFactor Authentication | O1: Third party/ AD username | P1: Timezone | Q1: Shift Duration | R1: Locations | S1: Reporting To
A2: Mohitv | B2: PT-PAT-06744 | D2: PRE 1 - Care from Nurses|Incident Reporter|QI Viewer|Incident Analyst|Audit User|PRE 1 - Nursing Services|Audit Incharge | E2: Paras Patna | F2: NURSING | L2: 24-Apr-2026 10:49 am | M2: Yes | N2: No
A3: preetamsaha | B3: PT-PAT-05069 | D3: Incident Reporter|QI Viewer|Incident Analyst|Audit User|Incident Admin|Audit Incharge|QI Admin | E3: Paras Patna | J3: 8017814192 | K3: quality.pat@parashospitals.com | L3: 24-Mar-2023 11:49 am | M3: No | N3: No
A4: jinubenny | B4: PT-PAT-03799 | D4: Incident Reporter|QI Viewer | E4: Paras Patna | F4: NURSING | J4: 7994723353 | K4: ns2pat@parashospitals.com | M4: Yes | N4: No
A5: shahinahmed | B5: PT-PAT-05111 | D5: Incident Reporter|QI Viewer|Audit User - Ambulance Response Time|Audit User - Patient Arrival Audit|Feedback Collector | E5: Paras Patna | F5: GUEST RELATIONS | J5: 7076114697 | K5: gre.patna@parashospitals.com | L5: 02-Jan-2024 05:08 pm | M5: No | N5: No
A6: SOMNATHMUKHARJEE | B6: pt-pat-05815 | D6: Feedback Duplicator|QI Viewer|PRE 0 - Staff Responsiveness and Behaviour|PRE 1 - Staff Responsiveness and Behaviour|PRE 1|Feedback Dashboard Viewer|PRE 1 - Paras Updates|Audit User - Patient Arrival Audit|Feedback Collector|PRE 0|Feedback Review Reassigner | E6: Paras Patna | F6: GUEST RELATIONS | J6: 8391917334 | K6: guestrelations.patna@parashospitals.com | L6: 03-Jun-2025 05:54 pm | M6: Yes | N6: No
A7: sanjooyadav | B7: PT-PAT-03787 | D7: Incident Reporter|QI Viewer | E7: Paras Patna | F7: NURSING | J7: 9670265111 | K7: ns1pat@parashospitals.com | M7: Yes | N7: No
A8: dhanjeetk | B8: PT-PAT-06941 | D8: Feedback Duplicator|QI Viewer|Feedback Leadership Dashboard Viewer|Feedback Dashboard Viewer|Audit User - Patient Arrival Audit|Feedback Collector|Guest Relations User | E8: Paras Patna | F8: HOSPITAL OPERATIONS | G8: Dhanjeet | I8: Kumar | J8: 7992430572 | K8: itpatna@parashospitals.com | L8: 22-May-2026 04:30 pm | M8: Yes | N8: No | Q8: ~-~
A9: kmgitanjalee | B9: PT-PAT-04187 | D9: Incident Reporter|QI Viewer | E9: Paras Patna | F9: NURSING | J9: 7275981209 | K9: nsgrpat@parashosiptals.com | M9: Yes | N9: No
A10: RAJEEVBHANDARI | B10: PT-PAT-05498 | D10: Incident Reporter|QI Viewer|Incident Analyst|Incident Dashboard Viewer|Audit Dashboard Viewer|Feedback Dashboard Viewer|PRE 3 | E10: Paras Patna | F10: HOSPITAL OPERATIONS | J10: 9031812313 | K10: zdpatna@parashospitals.com | L10: 15-May-2023 10:19 am | M10: No | N10: No
A11: sumansarikasinha | B11: PT-PAT-04047 | D11: Incident Reporter|QI Viewer | E11: Paras Patna | F11: NURSING | J11: 7870178723 | K11: ns5pat@parashospitals.com | M11: Yes | N11: No
A12: drsrinarayan | B12: PT-PAT-00231 | D12: Incident Reporter|QI Viewer|Incident Analyst|Audit Incharge - Prophylactic Antibiotic Compliance Audit|Audit Incharge - CPR Audit | E12: Paras Patna | F12: ANESTHESIOLOGY | J12: 9835293334 | K12: drsrirayan@parashospitals.com | M12: Yes | N12: No
A13: RitikN | B13: GG-GUR-10628 | D13: Incident Incharge|PRE 0 - Pharmacy|Incident Admin|PRE 1 - Pharmacy|PRE 2 - Pharmacy|Feedback Leadership Dashboard Viewer|PRE 3 - Pharmacy|Audit Dashboard Viewer|Incident Dashboard Viewer|Feedback Dashboard Viewer|Feedback Escalation Matrix Viewer|Audit User - Pharmacy Rejected Before GRN Audit | E13: Paras Patna | F13: OP PHARMACY|Pharmacy | G13: RITIK | I13: NAGAR | J13: 9350648327 | K13: ritik.nagar@parashospitals.com | L13: 26-May-2026 08:22 am | M13: Yes | N13: No | P13: Asia/Calcutta
A14: nehamehta | B14: PT-PAT-01399 | D14: Incident Reporter|QI Viewer | E14: Paras Patna | F14: NURSING | J14: 9835834915 | K14: ns4pat@parashospitals.com | L14: 22-Dec-2022 04:44 pm | M14: Yes | N14: No
A15: seemabaxla | B15: PT-PAT-03743 | D15: Incident Reporter|QI Viewer | E15: Paras Patna | F15: NURSING | J15: 7632922606 | K15: ns3pat@parashospitals.com | M15: Yes | N15: No
A16: rajishkr | B16: PT-PAT-05017 | D16: Incident Reporter|QI Viewer|Audit User | E16: Paras Patna | F16: NURSING | J16: 7003080165 | K16: nursing.supervisors@parashospitals.com | L16: 17-Feb-2023 08:40 pm | M16: Yes | N16: No
A17: ajmerikhatoon | B17: PT-PAT-04064 | D17: Incident Reporter|QI Viewer | E17: Paras Patna | F17: NURSING | J17: 7369807021 | K17: ns4pat@parashospitals.com | M17: Yes | N17: No
A18: adm_cell_PT | D18: QI Viewer|Incident Analyst|PRE 0 - Admission Experience | E18: Paras Patna | F18: Admissions | J18: 7283000915 | K18: it.his@parashospitals.com | M18: Yes | N18: No
A19: josphinmurmu | B19: PT-PAT-04998 | D19: Incident Reporter|QI Viewer | E19: Paras Patna | F19: NURSING | J19: 8178563377 | K19: ns5pat@parashospitals.com | M19: Yes | N19: No
A20: ROHANSHARMA | B20: PT-PAT-05351 | D20: Incident Reporter|QI Viewer|Audit User - Ambulance Response Time|Feedback Collector | E20: Paras Patna | J20: 7047680689 | K20: gre.pat@parashospitals.com | L20: 06-May-2023 01:32 pm | M20: No | N20: No
A21: RaviRanjanKumar | B21: PT-PAT-05681 | D21: QI Viewer|Incident Dashboard Viewer|Audit User - Adherence to safety precautions in Laboratory|Audit Incharge - Adherence to safety precautions in Laboratory|PRE 0 - Lab Services|PRE 1 - Lab Services|PRE 2 - Lab Services|PRE 3 - Lab Services | E21: Paras Patna | F21: Pathology | J21: 7631260747 | K21: raviranjan.kumar@parashospitals.com | L21: 15-Oct-2025 02:04 pm | M21: Yes | N21: No
A22: drkapilgarg | B22: drkapilgarg | D22: QI Viewer|Audit User|Incident Dashboard Viewer|Audit Dashboard Viewer|Feedback Dashboard Viewer | E22: Paras Patna | F22: GENERAL & ADMINISTRTIVE SERVICES | J22: 0000000000 | K22: it.his@parashospitals.com | L22: 31-Mar-2026 01:50 pm | M22: Yes | N22: No
A23: kalaivani | D23: Audit User|Audit Incharge|Audit Admin|Audit Configuration Admin|PRO|Incident Reporter|Incident Incharge|QI Viewer|Incident Analyst|QI Owner|Incident Admin|Hospital Statistics User|Hospital Statistics Admin|QI Admin | E23: Paras Patna | F23: GENERAL & ADMINISTRTIVE SERVICES | L23: 24-Jan-2025 12:34 pm | M23: Yes | N23: No
A24: ipd_sup_PT | D24: QI Viewer|Incident Analyst|PRE 0 - OPD Billing|PRE 0 - IPD Billing | E24: Paras Patna | F24: BILLING | J24: 08406001653 | K24: it.his@parashospitals.com | M24: Yes | N24: No
A25: sudhakarm | B25: PT-PAT-06791 | D25: PRE 2 - Dietician|Audit User|Audit Incharge|Feedback Dashboard Viewer|PRE 1 - Doctor Services|PRE 2 - Doctor Services|PRE 2 - Medical Equipment|Incident RCA Reviewer|QI Viewer|Incident Analyst|PRE 2 - ECG and ECHO|PRE 3 - ECG and ECHO|Hospital Statistics Admin - General Statistics|PRE 2 - Care from Doctors | E25: Paras Patna | F25: MEDICAL SERVICES | G25: Dr. Sudhakar Mishra | J25: 9939108739 | K25: drsudhakar.mishra@parashospitals.com | L25: 25-May-2026 10:21 am | M25: Yes | N25: No | Q25: ~-~
A26: arteekumari | B26: PT-PAT-04188 | D26: Incident Reporter|QI Viewer | E26: Paras Patna | F26: NURSING | J26: 9565918850 | K26: ns5pat@parashospitals.com | M26: Yes | N26: No
A27: rekhaemmanuel | B27: PT-PAT-04864 | D27: Incident Reporter|QI Viewer|Audit User | E27: Paras Patna | F27: NURSING | J27: 9631326070 | K27: ns2pat@parashospitals.com | L27: 17-May-2026 12:46 am | M27: Yes | N27: No
A28: arunkumar | B28: PT-PAT-04302 | D28: Incident Reporter|QI Viewer | E28: Paras Patna | F28: NURSING | J28: 9709928887 | K28: ns1pat@parashospitals.com | M28: Yes | N28: No
A29: rejeeshkumarr | B29: PT-PAT-02043 | D29: Incident Reporter|QI Viewer|Audit User | E29: Paras Patna | F29: NURSING | J29: 9947706363 | K29: nursing.supervisors@parashospitals.com | L29: 24-Jul-2023 12:54 pm | M29: Yes | N29: No
A30: syedarfiahmad | B30: PT-PAT-03327 | D30: Incident Reporter|QI Viewer | E30: Paras Patna | F30: NURSING | J30: 9015965427 | K30: ns4pat@parashospitals.com | M30: Yes | N30: No
A31: SONI.KUMARI | B31: PT-PAT-05900 | D31: Feedback Duplicator|QI Viewer|Audit User - Ambulance Response Time|PRE 0 - Staff Responsiveness and Behaviour|PRE 1 - Staff Responsiveness and Behaviour|PRE 1|Feedback Dashboard Viewer|PRE 1 - Paras Updates|Audit User - Patient Arrival Audit|Feedback Collector|PRE 0|Feedback Review Reassigner | E31: Paras Patna | F31: GUEST RELATIONS | J31: 8252749770 | K31: gre.pat@parashospitals.com | L31: 02-Mar-2024 03:46 pm | M31: Yes | N31: No
A32: NandiniGoswami | B32: pt-pat-05469 | D32: Feedback Duplicator|QI Viewer|PRE 0 - Staff Responsiveness and Behaviour|PRE 1 - Staff Responsiveness and Behaviour|PRE 1|Feedback Dashboard Viewer|PRE 1 - Paras Updates|Audit User - Patient Arrival Audit|Feedback Collector|PRE 0|Feedback Review Reassigner | E32: Paras Patna | J32: 7296079345 | L32: 04-May-2024 07:20 pm | M32: No | N32: No
A33: sabitadevi | B33: PT-PAT-00279 | D33: Incident Reporter|QI Viewer | E33: Paras Patna | F33: NURSING | J33: 9334429930 | K33: ns5pat@parashospitals.com | M33: Yes | N33: No
A34: jyotipandey | B34: PT-PAT-03864 | D34: Incident Reporter|QI Viewer | E34: Paras Patna | F34: NURSING | J34: 9792121998 | K34: ns4pat@parashospitals.com | M34: Yes | N34: No
A35: kumarijyoti | B35: PT-PAT-04241 | D35: Incident Reporter|QI Viewer | E35: Paras Patna | F35: NURSING | J35: 7897141280 | K35: ns1pat@parashospitals.com | M35: Yes | N35: No
A36: lokeshsingh | B36: GG-GUR-07852 | D36: Translator|Audit User|Audit Incharge|Audit Admin|Audit Configuration Admin|PRE 1|PRE 2|PRE 3|PRO|PRA|PRE 0|Guest Relations User|Feedback Review Reassigner|Feedback Configuration Admin|Incident Reporter|Incident Incharge|Incident Analyst|Incident Admin|Incident Advisor|Incident Officer|Incident Dashboard Viewer|Incident Configuration Admin|Audit User - Active file audit|Audit Incharge - Active file audit|Audit User - Call Bell Response Audit|Audit Incharge - Call Bell Response Audit|Audit User - TAT Adherence Audit|Audit Incharge - TAT Adherence Audit|Audit User - IPSG Audit|Audit Incharge - IPSG Audit|Audit User - HAPU Audit|Audit Incharge - HAPU Audit|Audit User - Ambulance Response Time|Audit Incharge - Ambulance Response Time|Audit User - Injection safety|Audit Incharge - Injection safety|Audit User - Prophylactic Antibiotic Compliance Audit|Audit Incharge - Prophylactic Antibiotic Compliance Audit|Audit User - Nursing Handover Audit|Audit Incharge - Nursing Handover Audit|Audit User - Nurse-Patient Ratio|Audit Incharge - Nurse-Patient Ratio|Audit User - Hand hygiene|Audit Incharge - Hand hygiene|Audit User - Passive file audit|Audit Incharge - Passive file audit|Audit User - Infusion safety|Audit Incharge - Infusion safety|Audit User - IP Prescription Audit|Audit Incharge - IP Prescription Audit|Audit User - Surgical safety checklist|Audit Incharge - Surgical safety checklist|Audit User - Biomedical Waste Management Audit|Audit Incharge - Biomedical Waste Management Audit|Audit User - Code Black - Mock drill|Audit Incharge - Code Black - Mock drill|Audit User - Critical Value Report Audit|Audit Incharge - Critical Value Report Audit|Audit User - CPR Audit|Audit Incharge - CPR Audit|Audit User - Patient identification|Audit Incharge - Patient identification|Audit User - Oral medication|Audit Incharge - Oral medication|Audit User - STROKE|Audit Incharge - STROKE|Audit User - Peer review of Imaging test report|Audit Incharge - Peer review of Imaging test report|Audit User - Code Hazmat - Mock drill|Audit Incharge - Code Hazmat - Mock drill|Audit User - Correlation with clinical diagnosis (Laboratory)|Audit Incharge - Correlation with clinical diagnosis (Laboratory)|Audit User - Pain Assessment Checklist|Audit Incharge - Pain Assessment Checklist|Audit User - Code Pink - Mock drill|Audit Incharge - Code Pink - Mock drill|Audit User - STEMI|Audit Incharge - STEMI|Audit User - Doctors Handover Audit|Audit Incharge - Doctors Handover Audit|Audit User - Adherence to safety precautions in Radiology / Cathlab / OT|Audit Incharge - Adherence to safety precautions in Radiology / Cathlab / OT|Audit User - SEPSIS PROTOCOL|Audit Incharge - SEPSIS PROTOCOL|Audit User - ER Prescription Audit|Audit Incharge - ER Prescription Audit|Audit User - Code Violet - Mock drill|Audit Incharge - Code Violet - Mock drill|Audit User - Drug Reconciliation Audit|Audit Incharge - Drug Reconciliation Audit|Audit User - CSSD Recall - Mock drill|Audit Incharge - CSSD Recall - Mock drill|Audit User - Code Red - Mock drill|Audit Incharge - Code Red - Mock drill|Audit User - Crash cart audit checklist|Audit Incharge - Crash cart audit checklist|Audit User - OP Prescription Audit|Audit Incharge - OP Prescription Audit|Audit User - Code Yellow - Mock drill|Audit Incharge - Code Yellow - Mock drill|Audit User - Correlation with clinical diagnosis (Radiology)|Audit Incharge - Correlation with clinical diagnosis (Radiology)|Audit User - Code Blue - Mock drill|Audit Incharge - Code Blue - Mock drill|Audit User - Adherence to safety precautions in Laboratory|Audit Incharge - Adherence to safety precautions in Laboratory|Audit User - TRAUMA Protocol|Audit Incharge - TRAUMA Protocol|PRE 0 - Diagnostics|PRE 1 - Diagnostics|PRE 2 - Diagnostics|PRE 3 - Diagnostics|PRE 0 - Admission Experience|PRE 1 - Admission Experience|PRE 2 - Admission Experience|PRE 3 - Admission Experience|Audit Dashboard Viewer|PRE 0 - Food Services and Dietician Rounds|PRE 1 - Food Services and Dietician Rounds|PRE 2 - Food Services and Dietician Rounds|PRE 3 - Food Services and Dietician Rounds|PRE 0 - Professional - Technical Competencies|PRE 1 - Professional - Technical Competencies|PRE 2 - Professional - Technical Competencies|PRE 3 - Professional - Technical Competencies|PRE 0 - Care from Nurses|PRE 1 - Care from Nurses|PRE 2 - Care from Nurses|PRE 3 - Care from Nurses|PRE 0 - Staff Responsiveness and Behaviour|PRE 1 - Staff Responsiveness and Behaviour|PRE 2 - Staff Responsiveness and Behaviour|PRE 3 - Staff Responsiveness and Behaviour|PRE 0 - Hospital Environment|PRE 1 - Hospital Environment|PRE 2 - Hospital Environment|PRE 3 - Hospital Environment|PRE 0 - Discharge Information|PRE 1 - Discharge Information|PRE 2 - Discharge Information|PRE 3 - Discharge Information|PRE 0 - Affective Support|PRE 1 - Affective Support|PRE 2 - Affective Support|PRE 3 - Affective Support|PRE 0 - Emergency Room Environment|PRE 1 - Emergency Room Environment|PRE 2 - Emergency Room Environment|PRE 3 - Emergency Room Environment|PRE 0 - Billing|PRE 1 - Billing|PRE 2 - Billing|PRE 3 - Billing|PRE 0 - Call Centre|PRE 1 - Call Centre|PRE 2 - Call Centre|PRE 3 - Call Centre|PRE 0 - ICU/CCU Care|PRE 1 - ICU/CCU Care|PRE 2 - ICU/CCU Care|PRE 3 - ICU/CCU Care|PRE 0 - Physiotherapy|PRE 1 - Physiotherapy|PRE 2 - Physiotherapy|PRE 3 - Physiotherapy|PRE 0 - Care from Doctors|PRE 1 - Care from Doctors|PRE 2 - Care from Doctors|PRE 3 - Care from Doctors|PRE 0 - Health Information|PRE 1 - Health Information|PRE 2 - Health Information|PRE 3 - Health Information|PRE 0 - Decisional Control|PRE 1 - Decisional Control|PRE 2 - Decisional Control|PRE 3 - Decisional Control|PRE 0 - Security Services|PRE 1 - Security Services|PRE 2 - Security Services|PRE 3 - Security Services|PRE 0 - Paras Updates|PRE 1 - Paras Updates|PRE 2 - Paras Updates|PRE 3 - Paras Updates|Audit User - Medication Audit|Audit Incharge - Medication Audit|Audit User - Phlebitis Audit|Audit Incharge - Phlebitis Audit|Audit User - NABH Safety Audit|Audit Incharge - NABH Safety Audit|Audit User - Clinical Safety Audit|Audit Incharge - Clinical Safety Audit|Hospital Statistics User|Hospital Statistics Admin|Hospital Statistics Configuration Admin|QI Admin|QI Configuration view|Hospital Statistics Admin - General Statistics|Hospital Statistics User - General Statistics|PRE 0 - IPD Billing|PRE 1 - IPD Billing|PRE 2 - IPD Billing|PRE 3 - IPD Billing|PRE 0 - Technology|PRE 1 - Technology|PRE 2 - Technology|PRE 3 - Technology|Feedback Collector|PRE 0 - Cleanliness|PRE 1 - Cleanliness|PRE 2 - Cleanliness|PRE 3 - Cleanliness|PRE 0 - Dietician|PRE 1 - Dietician|PRE 2 - Dietician|PRE 3 - Dietician|PRE 0 - Pharmacy|PRE 1 - Pharmacy|PRE 2 - Pharmacy|PRE 3 - Pharmacy|PRE 0 - Radiology or Lab Services|PRE 1 - Radiology or Lab Services|PRE 2 - Radiology or Lab Services|PRE 3 - Radiology or Lab Services|PRE 0 - Medical Equipment|PRE 1 - Medical Equipment|PRE 2 - Medical Equipment|PRE 3 - Medical Equipment|PRE 0 - Food and Beverage|PRE 1 - Food and Beverage|PRE 2 - Food and Beverage|PRE 3 - Food and Beverage|PRE 0 - GDA|PRE 1 - GDA|PRE 2 - GDA|PRE 3 - GDA|PRE 0 - Security|PRE 1 - Security|PRE 2 - Security|PRE 3 - Security|PRE 0 - OPD / ER Billing|PRE 1 - OPD / ER Billing|PRE 2 - OPD / ER Billing|PRE 3 - OPD / ER Billing|PRE 0 - Maintenance|PRE 1 - Maintenance|PRE 2 - Maintenance|PRE 3 - Maintenance|PRE 0 - Nursing Services|PRE 1 - Nursing Services|PRE 2 - Nursing Services|PRE 3 - Nursing Services|PRE 0 - Doctor Services|PRE 1 - Doctor Services|PRE 2 - Doctor Services|PRE 3 - Doctor Services|PRE 0 - Discharge|PRE 1 - Discharge|PRE 2 - Discharge|PRE 3 - Discharge|Incident RCA Approver|Incident RCA Reviewer|QI Viewer|QI Owner|Audit User - Nursing Documentation Audit|Audit Incharge - Nursing Documentation Audit|PRE 0 - GDA Services|PRE 1 - GDA Services|PRE 2 - GDA Services|PRE 3 - GDA Services|PRE 0 - Admission Process|PRE 1 - Admission Process|PRE 2 - Admission Process|PRE 3 - Admission Process|PRE 0 - Housekeeping Services|PRE 1 - Housekeeping Services|PRE 2 - Housekeeping Services|PRE 3 - Housekeeping Services|PRE 0 - Discharge Process|PRE 1 - Discharge Process|PRE 2 - Discharge Process|PRE 3 - Discharge Process|SLA and Configurations Viewer|User Account Manager|Feedback Dashboard Viewer|PRE 0 - Radiology Services|PRE 1 - Radiology Services|PRE 2 - Radiology Services|PRE 3 - Radiology Services|PRE 0 - Lab Services|PRE 1 - Lab Services|PRE 2 - Lab Services|PRE 3 - Lab Services|Feedback Duplicator|Audit User - CLABSI Bundle Audit|Audit Incharge - CLABSI Bundle Audit|Audit User - CAUTI Bundle Audit|Audit Incharge - CAUTI Bundle Audit|Audit User - VAE Bundle Audit|Audit Incharge - VAE Bundle Audit|Botomate Viewer|Audit User - Patient Arrival Audit|Audit Incharge - Patient Arrival Audit|Non-Conformance Reporter|Non-Conformance Admin|Non-Conformance Champion|Non-Conformance Officer|Non-Conformance Configuration Admin|Hospital Statistics Admin - Admission TAT Statistics|Hospital Statistics User - Admission TAT Statistics|Hospital Statistics Admin - Discharge TAT Statistics|Hospital Statistics User - Discharge TAT Statistics|Hospital Statistics Admin - OPD TAT Statistics|Hospital Statistics User - OPD TAT Statistics|Feedback Leadership Dashboard Viewer|Survey Viewer|Survey Owner|Survey Admin|Feedback Escalation Matrix Viewer|Audit Escalation Matrix|Hospital Stats Escalation Matrix|Hospital Statistics Admin - Pharmacy Statistics|Hospital Statistics User - Pharmacy Statistics|Hospital Statistics Admin - ICU Statistics|Hospital Statistics User - ICU Statistics|Hospital Statistics Admin - Operating Theatre Statistics|Hospital Statistics User - Operating Theatre Statistics|Hospital Statistics Admin - Emergency Department Statistics|Hospital Statistics User - Emergency Department Statistics|Hospital Statistics Admin - Ethics Committee Statistics|Hospital Statistics User - Ethics Committee Statistics|Hospital Statistics Admin - Blood Bank statistics|Hospital Statistics User - Blood Bank statistics|Hospital Statistics Admin - Cathlab Statistics|Hospital Statistics User - Cathlab Statistics|Hospital Statistics Admin - Radiology Statistics|Hospital Statistics User - Radiology Statistics|Hospital Statistics Admin - Infection control Statistics|Hospital Statistics User - Infection control Statistics|Hospital Statistics Admin - Laboratory Statistics|Hospital Statistics User - Laboratory Statistics|Hospital Statistics Admin - HR Statistics|Hospital Statistics User - HR Statistics|Non-Conformance Reporter - Admission and Discharge|Non-Conformance Admin - Admission and Discharge|Non-Conformance Reporter - Operation Theatre|Non-Conformance Admin - Operation Theatre|Non-Conformance Reporter - ICU|Non-Conformance Admin - ICU|Non-Conformance Reporter - Blood Bank|Non-Conformance Admin - Blood Bank|Non-Conformance Reporter - Laboratory|Non-Conformance Admin - Laboratory|Non-Conformance Reporter - Radiology|Non-Conformance Admin - Radiology|Non-Conformance Reporter - Emergency|Non-Conformance Admin - Emergency|Non-Conformance Reporter - Pharmacy|Non-Conformance Admin - Pharmacy|Non-Conformance Reporter - tres|Non-Conformance Admin - tres|Audit User - Return to emergency within 72 hrs with similar complaints Audit|Audit Incharge - Return to emergency within 72 hrs with similar complaints Audit|Audit User - Blood Wastage Audit|Audit Incharge - Blood Wastage Audit|Audit User - Unplanned discharges Audit|Audit Incharge - Unplanned discharges Audit|Audit User - Readmission to Hospital within 48 Hours Audit|Audit Incharge - Readmission to Hospital within 48 Hours Audit|Audit User - Unplanned Ventilation following Anaesthesia Audit|Audit Incharge - Unplanned Ventilation following Anaesthesia Audit|Audit User - Pharmacy Local Purchase Audit|Audit Incharge - Pharmacy Local Purchase Audit|Audit User - Radiology Re-do Audit|Audit Incharge - Radiology Re-do Audit|Audit User - Radiology Imaging Modality Change Audit|Audit Incharge - Radiology Imaging Modality Change Audit|Audit User - Blood Bank Under Collection Audit|Audit Incharge - Blood Bank Under Collection Audit|Audit User - Readmission to ICU within 48 Hours Audit|Audit Incharge - Readmission to ICU within 48 Hours Audit|Audit User - Laboratory Culture Contamination Audit|Audit Incharge - Laboratory Culture Contamination Audit|Audit User - Blood Bank Re-do Audit|Audit Incharge - Blood Bank Re-do Audit|Audit User - Blood Bank Reagent Stock out Audit|Audit Incharge - Blood Bank Reagent Stock out Audit|Audit User - Pharmacy Rejected Before GRN Audit|Audit Incharge - Pharmacy Rejected Before GRN Audit|Audit User - Blood Bank Reporting error Audit|Audit Incharge - Blood Bank Reporting error Audit|Audit User - Modification of Anesthesia plan Audit|Audit Incharge - Modification of Anesthesia plan Audit|Audit User - Unplanned return to Operation Theatre Audit|Audit Incharge - Unplanned return to Operation Theatre Audit|Audit User - Rescheduling or Cancellation of surgeries Audit|Audit Incharge - Rescheduling or Cancellation of surgeries Audit|Audit User - Pharmacy Stock Out Audit|Audit Incharge - Pharmacy Stock Out Audit|Audit User - Intra-Operative change in Surgery Audit|Audit Incharge - Intra-Operative change in Surgery Audit|Audit User - Unplanned Post-Operative Admission to Surgical ICU Audit|Audit Incharge - Unplanned Post-Operative Admission to Surgical ICU Audit|Audit User - Pharmacy Variations in Procurement Process Audit|Audit Incharge - Pharmacy Variations in Procurement Process Audit|Audit User - Laboratory Sample Rejection Audit|Audit Incharge - Laboratory Sample Rejection Audit|Audit User - Laboratory Re-do Audit|Audit Incharge - Laboratory Re-do Audit|Audit User - High TAT for issuing or receiving blood from blood-bank Audit|Audit Incharge - High TAT for issuing or receiving blood from blood-bank Audit|Hospital Statistics Admin - Nurse Patient Ratio Statistics|Hospital Statistics User - Nurse Patient Ratio Statistics|Call Center reviewer|Hospital Statistics Admin - POS|Hospital Statistics User - POS|Hospital Statistics Admin - Quality Statistics|Hospital Statistics User - Quality Statistics|Hospital Statistics Admin - security Stats|Hospital Statistics User - security Stats|Audit User - Multi-Disciplinary Tumor Board - MDT|Audit Incharge - Multi-Disciplinary Tumor Board - MDT|PRE 0 - ECG and ECHO|PRE 1 - ECG and ECHO|PRE 2 - ECG and ECHO|PRE 3 - ECG and ECHO|PRE 0 - OPD Billing|PRE 1 - OPD Billing|PRE 2 - OPD Billing|PRE 3 - OPD Billing|Audit User - Spill Kit Checklist|Audit Incharge - Spill Kit Checklist|Audit User - HAZMAT AUDIT CHECKLIST|Audit Incharge - HAZMAT AUDIT CHECKLIST|Audit User - Pre and Post Procedure Financial Counselling|Audit Incharge - Pre and Post Procedure Financial Counselling|Audit User - Counselling or Briefing About The Room Services|Audit Incharge - Counselling or Briefing About The Room Services|Audit User - RRT Mockdrill - Mock drill|Audit Incharge - RRT Mockdrill - Mock drill|Audit User - RRT Mockdrill Audit|Audit Incharge - RRT Mockdrill Audit|Audit User - Code Orange - Mock drill|Audit Incharge - Code Orange - Mock drill | E36: Paras Patna | F36: INFORMATION TECHNOLOGY|IT | J36: 8800764545 | K36: lokesh.singh@parashospitals.com | L36: 25-May-2026 05:46 pm | M36: Yes | N36: No
A37: kumaripriyanka | B37: PT-PAT-04257 | D37: Incident Reporter|QI Viewer | E37: Paras Patna | F37: NURSING | J37: 8004050087 | K37: ns3pat@parashospitals.com | M37: Yes | N37: No
A38: abhishekkumarsharma | B38: PT-PAT-04697 | D38: Incident Reporter|QI Viewer|Incident Analyst|PRE 1 - Staff Responsiveness and Behaviour | E38: Paras Patna | J38: 8827478250 | K38: abhishek.sharma@parashospitals.com | M38: No | N38: No
A39: mubashhir | D39: QI Viewer|Audit User|Audit Admin|Audit Configuration Admin | E39: Paras Patna | F39: GENERAL & ADMINISTRTIVE SERVICES | L39: 10-Mar-2025 04:35 pm | M39: Yes | N39: No
A40: kumarianamikasinha | B40: PT-PAT-00921 | D40: Incident Reporter|QI Viewer | E40: Paras Patna | F40: NURSING | J40: 9852575665 | K40: nsgrpat@parashosiptals.com | M40: Yes | N40: No
A41: drmdshamimfarooqui | B41: PT-PAT-04253 | D41: Incident Reporter|QI Viewer|Incident Analyst|Audit User - STROKE|Audit User - SEPSIS PROTOCOL|Audit User - TRAUMA Protocol|Audit User - STEMI | E41: Paras Patna | J41: 7840068786 | K41: ns5pat@parashospitals.com | M41: No | N41: No
A42: sec_sup_PT | D42: QI Viewer|Incident Analyst|PRE 1 - Security Services|PRE 0 - Security | E42: Paras Patna | F42: SECURITY | J42: 8406001660 | K42: mumtaz.ali@parashospitals.com | L42: 05-May-2026 02:00 pm | M42: Yes | N42: No
A43: subhraghatak | B43: PT-PAT-06748 | D43: Incident Reporter|PRE 1 - Care from Nurses|PRE 2 - Care from Nurses|QI Viewer|Incident Analyst|Audit User|Audit Incharge|PRE 1 - Nursing Services|PRE 2 - Nursing Services | E43: Paras Patna | F43: NURSING | G43: Subhra | I43: Ghatak | J43: 8240613095 | L43: 21-May-2026 03:36 pm | M43: Yes | N43: No
A44: ranshulaggarwal | D44: QI Viewer|QI Owner|Incident Advisor|Audit Admin|Incident Dashboard Viewer|Audit Dashboard Viewer|QI Admin|QI Configuration view|Feedback Dashboard Viewer|Audit User - Patient Arrival Audit|PRA | E44: Paras Patna | F44: HUMAN RESOURCE | J44: 0000000000 | K44: ranshul.aggarwal@parashospitals.com | L44: 23-Aug-2023 02:09 pm | M44: No | N44: No
A45: pramodpp | B45: PT-PAT-04872 | D45: Incident Reporter|QI Viewer|Audit User | E45: Paras Patna | F45: NURSING | J45: 8210881478 | K45: ns4pat@parashospitals.com | M45: Yes | N45: No
A46: rubykumari | B46: PT-PAT-03745 | D46: Incident Reporter|QI Viewer | E46: Paras Patna | F46: NURSING | J46: 9102906060 | K46: ns5pat@parashospitals.com | M46: Yes | N46: No
A47: anuradha | B47: PT-PAT-04177 | D47: Incident Reporter|QI Viewer | E47: Paras Patna | F47: NURSING | J47: 9170258806 | K47: ns4pat@parashospitals.com | M47: Yes | N47: No
A48: sanchayetaray | B48: PT-PAT-04888 | D48: Incident Reporter|QI Viewer|Audit User - Ambulance Response Time|Audit User - Patient Arrival Audit|Feedback Collector | E48: Paras Patna | F48: GUEST RELATIONS | J48: 8910632045 | K48: gre.pat@parashospitals.com | L48: 15-Apr-2023 03:45 pm | M48: Yes | N48: No
A49: ritayadav | B49: PT-PAT-04157 | D49: Incident Reporter|QI Viewer | E49: Paras Patna | F49: NURSING | J49: 6393416635 | K49: nsgrpat@parashosiptals.com | M49: Yes | N49: No
A50: alishamukhia | B50: PT-PAT-05895 | D50: QI Viewer|Incident Analyst|Feedback Dashboard Viewer|PRE 2|Audit User - Patient Arrival Audit|Audit Incharge - Patient Arrival Audit|Feedback Collector|Feedback Review Reassigner | E50: Paras Patna | J50: 9083924669 | K50: alisha.mukhia@parashospitals.com | L50: 04-Jun-2024 11:20 am | M50: No | N50: No
A51: ManikbirS | B51: GG-COR-07357 | D51: Incident Admin|Audit Incharge|Audit Admin|Feedback Leadership Dashboard Viewer|Feedback Dashboard Viewer|Hospital Statistics Admin - Quality Statistics | E51: Paras Patna | F51: HOSPITAL OPERATIONS | G51: Manikbir | I51: Singh | J51: 9876593619 | K51: drmanikbir.singh@parashealth.com | L51: 18-Mar-2026 05:24 pm | M51: Yes | N51: No
A52: runiyakujur | B52: PT-PAT-03130 | D52: Incident Reporter|QI Viewer | E52: Paras Patna | F52: NURSING | J52: 8292009690 | K52: ns3pat@parashospitals.com | M52: Yes | N52: No
A53: seemabara | B53: PT-PAT-01340 | D53: Incident Reporter|QI Viewer | E53: Paras Patna | F53: NURSING | J53: 9693624773 | K53: ns4pat@parashospitals.com | M53: Yes | N53: No
A54: vishalkumar | B54: PT-PAT-04036 | D54: Incident Reporter|QI Viewer | E54: Paras Patna | F54: BIOMEDICAL ENGINEERING | J54: 6207474258 | K54: biomedical.pat@parashospitals.com | L54: 21-Dec-2022 06:07 pm | M54: Yes | N54: No
A55: deeparainarazdan | B55: GG-GUR-07562 | D55: QI Viewer|Feedback Dashboard Viewer|PRO|Feedback Collector|Feedback Review Reassigner | E55: Paras Patna | F55: FOOD & BEVERAGES|GENERAL & ADMINISTRTIVE SERVICES | J55: 0000000000 | K55: deepa.raina@parashospitals.com | L55: 17-Apr-2026 03:42 pm | M55: Yes | N55: No
A56: gopalpandey | B56: PT-PAT-04858 | D56: Incident Reporter|QI Viewer|Incident Analyst | E56: Paras Patna | J56: 9953463301 | K56: gopal.pandey@parashospitals.com | M56: No | N56: No
A57: drchandankishore | B57: PT-PAT-04903 | D57: Incident Reporter|QI Viewer|Incident Analyst|Audit User - STROKE|Audit User - SEPSIS PROTOCOL|Audit User - TRAUMA Protocol|Audit User - STEMI | E57: Paras Patna | J57: 9431060299 | K57: ns5pat@parashospitals.com | M57: No | N57: No
A58: reenakumari | B58: PT-PAT-02973 | D58: Incident Reporter|QI Viewer | E58: Paras Patna | F58: NURSING | J58: 8789915731 | K58: ns4pat@parashospitals.com | M58: Yes | N58: No
A59: neethug | B59: PT-PAT-03439 | D59: Incident Reporter|QI Viewer | E59: Paras Patna | F59: NURSING | J59: 9605575137 | K59: ns5pat@parashospitals.com | M59: Yes | N59: No
A60: arpitapanja | B60: PT-PAT-05986 | D60: Feedback Duplicator|QI Viewer|PRE 0 - Staff Responsiveness and Behaviour|PRE 1 - Staff Responsiveness and Behaviour|PRE 1|Feedback Dashboard Viewer|PRE 1 - Paras Updates|Audit User - Patient Arrival Audit|Feedback Collector|Feedback Review Reassigner | E60: Paras Patna | F60: GUEST RELATIONS | J60: 9474540398 | K60: gre.pat@parashospitals.com | L60: 28-Jan-2026 11:45 pm | M60: Yes | N60: No
A61: drshashikishore | B61: PT-PAT-01940 | D61: Incident Reporter|QI Viewer|Incident Analyst|Audit Incharge - Surgical safety checklist|Audit Incharge - Prophylactic Antibiotic Compliance Audit|Audit Incharge - Biomedical Waste Management Audit|Audit Incharge - Code Hazmat - Mock drill|Audit Incharge - Code Orange - Mock drill|Audit Incharge - Hand hygiene|Audit Incharge - Phlebitis Audit|Audit Incharge - IPSG Audit | E61: Paras Patna | F61: CLINICAL LABORATORY | J61: 9135066681 | K61: drshashi.kishore@parashospitals.com | L61: 16-Dec-2022 05:24 pm | M61: Yes | N61: No
A62: ashutoshkumarsingh | B62: PT-PAT-05024 | D62: Incident Reporter|QI Viewer|Incident Analyst|Audit User | E62: Paras Patna | F62: HOUSEKEEPING | J62: 8795051170 | K62: hkpat@parashospitals.com | M62: Yes | N62: No
A63: dibyaram | B63: PT-PAT-04026 | D63: Incident Reporter|QI Viewer | E63: Paras Patna | F63: NURSING | J63: 6392206283 | K63: ns4pat@parashospitals.com | M63: Yes | N63: No
A64: narendrakumaryadav | B64: PT-PAT-04729 | D64: Incident Reporter|Audit User - Crash cart audit checklist|QI Viewer|Incident Analyst|Audit User - IP Prescription Audit|Audit User - OP Prescription Audit|Audit User - ER Prescription Audit|Audit User - Drug Reconciliation Audit|Audit User - Medication Audit|Audit User - IPSG Audit | E64: Paras Patna | F64: OP PHARMACY | J64: 9571368763 | K64: clinicalpharmacist.pat@parashospitals.com | L64: 19-Jul-2023 03:49 pm | M64: No | N64: No
A65: lalikumari | B65: PT-PAT-04023 | D65: Incident Reporter|QI Viewer | E65: Paras Patna | F65: NURSING | J65: 8051707046 | K65: nsgrpat@parashosiptals.com | M65: Yes | N65: No
A66: anuradhasingh | B66: GG-COR-06746 | D66: QI Viewer|QI Owner|Incident Advisor|Audit Admin|Incident Dashboard Viewer|Audit Dashboard Viewer|QI Admin|QI Configuration view|Feedback Dashboard Viewer | E66: Paras Patna | J66: 0000000000 | K66: it.his@parashospitals.com | L66: 31-Mar-2023 12:02 pm | M66: No | N66: No
A67: anjaleetamang | B67: PT-PAT-03053 | D67: Incident Reporter|QI Viewer | E67: Paras Patna | F67: NURSING | J67: 7004473320 | K67: ns3pat@parashospitals.com | M67: Yes | N67: No
A68: poonamgautam | B68: PT-PAT-04153 | D68: Incident Reporter|QI Viewer | E68: Paras Patna | F68: NURSING | J68: 8826549422 | K68: ns4pat@parashospitals.com | M68: Yes | N68: No
A69: swetakumari | B69: PT-PAT-04186 | D69: Incident Reporter|QI Viewer | E69: Paras Patna | F69: NURSING | J69: 7652078455 | K69: ns4pat@parashospitals.com | M69: Yes | N69: No
A70: gibiyajose | B70: PT-PAT-02163 | D70: Incident Reporter|QI Viewer|Audit User | E70: Paras Patna | F70: NURSING | J70: 8547841675 | K70: ns3pat@parashospitals.com | L70: 23-May-2023 12:41 pm | M70: Yes | N70: No
A71: pankajjha | B71: PT-PAT-05167 | D71: Incident Reporter|PRE 1 - Care from Nurses|QI Viewer|Incident Analyst|Audit User|Audit Incharge|PRE 1 - Nursing Services | E71: Paras Patna | J71: 7754019657 | K71: ns5pat@parashospitals.com | L71: 26-Sep-2023 12:12 pm | M71: No | N71: No
A72: harendrakumardivakar | B72: PT-PAT-01824 | D72: Incident Reporter|QI Viewer|Incident Analyst|Hospital Statistics Admin - General Statistics|Hospital Statistics User - General Statistics|Hospital Statistics User - Quality Statistics|Audit User - Passive file audit | E72: Paras Patna | F72: MEDICAL RECORD DEPARTMENT | J72: 9631412647 | K72: harendra.divakar@parashospitals.com | L72: 21-May-2026 10:34 am | M72: Yes | N72: No
A73: gourishankarprasad | B73: PT-PAT-04079 | D73: Incident Reporter|QI Viewer|Incident Analyst|Audit User - Code Yellow - Mock drill|Audit User - Biomedical Waste Management Audit|Audit User - Code Hazmat - Mock drill|Audit User - Code Black - Mock drill|Audit User - Code Violet - Mock drill|Audit User - Code Blue - Mock drill|Audit User - Code Pink - Mock drill|PRE 1 - Medical Equipment|Audit User - Code Red - Mock drill | E73: Paras Patna | J73: 7004359005 | K73: gouri.prasad@parashospitals.com | L73: 25-Jan-2024 12:33 am | M73: No | N73: No
A74: phc_sup_PT | D74: QI Viewer|Incident Analyst|PRE 0 - Pharmacy | E74: Paras Patna | F74: OP PHARMACY | J74: 7360008349 | K74: oppharmacypat@parashospitals.com | M74: Yes | N74: No
A75: rohitrpillai | B75: PT-PAT-01847 | D75: Incident Reporter|QI Viewer|Incident Analyst|Audit User|Audit Incharge | E75: Paras Patna | F75: NURSING | J75: 9162966075 | K75: nursingquality.patna@parashospitals.com | L75: 28-Jan-2023 12:37 pm | M75: No | N75: No
A76: suchitakujur | B76: PT-PAT-01347 | D76: Incident Reporter|QI Viewer | E76: Paras Patna | F76: NURSING | J76: 8102201940 | K76: nsgrpat@parashosiptals.com | M76: Yes | N76: No
A77: anitarajbhar | B77: PT-PAT-04173 | D77: Incident Reporter|QI Viewer | E77: Paras Patna | F77: NURSING | J77: 7408280296 | K77: ns3pat@parashospitals.com | M77: Yes | N77: No
A78: laxmibhargav | B78: PT-PAT-03845 | D78: Incident Reporter|QI Viewer | E78: Paras Patna | F78: NURSING | J78: 9682259151 | K78: ns2pat@parashospitals.com | M78: Yes | N78: No
A79: audituser_mdt | D79: Audit Incharge - Multi-Disciplinary Tumor Board - MDT|QI Viewer|Audit Dashboard Viewer|Audit User - Multi-Disciplinary Tumor Board - MDT | E79: Paras Patna | F79: GENERAL & ADMINISTRTIVE SERVICES | L79: 13-Sep-2025 06:54 pm | M79: Yes | N79: No
A80: nehamishra | B80: PT-PAT-5548 | D80: Incident Reporter|QI Viewer|Audit User - Ambulance Response Time|Audit User - Patient Arrival Audit|Feedback Collector | E80: Paras Patna | F80: GUEST RELATIONS | J80: 7759893726 | K80: guestrelations.patna@parashospitals.com | L80: 06-Oct-2023 10:45 am | M80: No | N80: No
A81: Drmmsayeed | B81: PT-PAT-05389 | D81: Incident Reporter|QI Viewer|Incident Analyst|Incident Dashboard Viewer|Audit Dashboard Viewer|Feedback Dashboard Viewer|PRE 3|PRO | E81: Paras Patna | F81: HOSPITAL OPERATIONS | J81: 7702519951 | K81: drmmsayeed@parashospitals.com | L81: 25-Mar-2023 03:41 pm | M81: No | N81: No
A82: shweta | B82: PT-PAT-04189 | D82: Incident Reporter|QI Viewer | E82: Paras Patna | F82: NURSING | J82: 7275713928 | K82: ns2pat@parashospitals.com | M82: Yes | N82: No
A83: anoopkumarsingh | B83: PT-PAT-02095 | D83: Incident Reporter|QI Viewer | E83: Paras Patna | F83: NURSING | J83: 7318529886 | K83: Chemodaycarens1pat@parashospitals.com] | M83: Yes | N83: No
A84: tech_it_PT | D84: QI Viewer|Incident Analyst|PRE 0 - Technology | E84: Paras Patna | F84: INFORMATION TECHNOLOGY | J84: 8406002655 | K84: itpat@parashospitals.com | L84: 17-Jan-2023 06:32 pm | M84: Yes | N84: No
A85: shashankteotia | B85: GG-COR-06702 | D85: QI Viewer|Audit Admin|Feedback Leadership Dashboard Viewer|Incident Dashboard Viewer|Audit Dashboard Viewer|Feedback Dashboard Viewer | E85: Paras Patna | F85: HUMAN RESOURCE | J85: 9899440055 | K85: shashank.teotia@parashospitals.com | L85: 09-Jul-2025 04:17 pm | M85: Yes | N85: No
A86: rajendrakumar | B86: PT-PAT-04258 | D86: Incident Reporter|QI Viewer | E86: Paras Patna | F86: NURSING | J86: 8858244553 | K86: ns4pat@parashospitals.com | M86: Yes | N86: No
A87: chandaneeyadav | B87: PT-PAT-03795 | D87: Incident Reporter|QI Viewer | E87: Paras Patna | F87: NURSING | J87: 6392468668 | K87: ns3pat@parashospitals.com | M87: Yes | N87: No
A88: edithdungdung | B88: PT-PAT-04049 | D88: Incident Reporter|QI Viewer | E88: Paras Patna | F88: NURSING | J88: 9515070204 | K88: ns4pat@parashospitals.com | M88: Yes | N88: No
A89: smritikumari | B89: PT-PAT-05568 | D89: Feedback Duplicator|QI Viewer|PRE 0 - Staff Responsiveness and Behaviour|PRE 1 - Staff Responsiveness and Behaviour|PRE 1|Feedback Dashboard Viewer|PRE 1 - Paras Updates|Audit User - Patient Arrival Audit|Feedback Collector|PRE 0|Feedback Review Reassigner | E89: Paras Patna | F89: GUEST RELATIONS | J89: 8674971219 | K89: gre.pat@parashospitals.com | L89: 11-May-2026 09:31 pm | M89: Yes | N89: No
A90: AnandMohan | B90: PT-PAT-06484 | D90: Feedback Duplicator|QI Viewer|PRE 0 - Staff Responsiveness and Behaviour|PRE 1 - Staff Responsiveness and Behaviour|PRE 1|Feedback Dashboard Viewer|PRE 1 - Paras Updates|Audit User - Patient Arrival Audit|Feedback Collector|PRE 0|Feedback Review Reassigner | E90: Paras Patna | F90: GUEST RELATIONS | J90: 8651084866 | K90: guestrelations.patna@parashospitals.com | L90: 20-May-2025 09:47 pm | M90: Yes | N90: No
A91: fb_sup_PT | D91: QI Viewer|Incident Analyst|PRE 0 - Food and Beverage | E91: Paras Patna | F91: FOOD & BEVERAGES | J91: 9525000083 | K91: amit.singh@parashospitals.com | M91: Yes | N91: No
A92: abhishekkumar | B92: PT-PAT-00244 | D92: Incident Reporter|QI Viewer|Incident Analyst|Audit User|Audit Incharge|PRE 2 - Admission Process|PRE 2 - Admission Experience|PRE 2 - Call Centre|PRE 2 - OPD / ER Billing | E92: Paras Patna | F92: GENERAL & ADMINISTRTIVE SERVICES | J92: 8252672281 | K92: kumar.abhishek@parashospitals.com | L92: 07-Aug-2025 10:50 am | M92: Yes | N92: No | P92: Asia/Kolkata
A93: sushmitajosephinekujur | B93: PT-PAT-04857 | D93: Incident Reporter|QI Viewer|Audit User | E93: Paras Patna | F93: NURSING | J93: 9110910879 | K93: itpatna@parashospitals.com | L93: 17-May-2026 12:53 pm | M93: Yes | N93: No
A94: shameerma | B94: PT-PAT-05070 | D94: Incident Reporter|QI Viewer|Audit User | E94: Paras Patna | F94: NURSING | J94: 8592963479 | K94: ns4pat@parashospitals.com | M94: Yes | N94: No
A95: debrinapandit | B95: PT-PAT-5549 | D95: Incident Reporter|QI Viewer|Audit User - Ambulance Response Time|Audit User - Patient Arrival Audit|Feedback Collector | E95: Paras Patna | F95: GUEST RELATIONS | J95: 7980222379 | K95: gre.pat@parashospitals.com | L95: 18-Sep-2023 12:47 pm | M95: No | N95: No
A96: kumarneeraj | B96: PT-PAT-06079 | D96: Incident Reporter|QI Viewer|Incident Analyst|Audit User|Audit Incharge | E96: Paras Patna | F96: FINANCE & ACCOUNTS | J96: 9810871948 | K96: neeraj.kumar@parashospitals.com | M96: Yes | N96: No
A97: pooja_saini | B97: PT-PAT-05357 | D97: QI Viewer|Incident Analyst|Audit Incharge|Feedback Dashboard Viewer|PRE 2|Audit User - Patient Arrival Audit | E97: Paras Patna | J97: 8375937403 | K97: pooja.saini@parashospitals.com | L97: 11-Apr-2023 02:06 pm | M97: No | N97: No
A98: archanachandra | B98: PT-PAT-02803 | D98: Incident Reporter|QI Viewer | E98: Paras Patna | F98: NURSING | J98: 7519654412 | K98: ns5pat@parashospitals.com | M98: Yes | N98: No
A99: drsantysajan | B99: GG-COR-06751 | D99: Incident Reporter|QI Viewer|QI Owner|Audit User|Incident Advisor|Audit Admin|Feedback Leadership Dashboard Viewer|Incident Dashboard Viewer|Audit Dashboard Viewer|QI Admin|Feedback Dashboard Viewer | E99: Paras Patna | J99: 7339645111 | K99: drsanty.sajan@parashospitals.com | L99: 21-Jun-2023 10:16 am | M99: No | N99: No
A100: anilkumaryadav | B100: PT-PAT-04255 | D100: Incident Reporter|QI Viewer | E100: Paras Patna | F100: NURSING | J100: 7271842033 | K100: ns5pat@parashospitals.com | M100: Yes | N100: No
...

Sheet Paras
A1: Sr. NO | B1: userName | C1: password | D1: departments | E1: roles | F1: units | G1: locations | H1: Mail ID | I1: Personal Phone | J1: employeeId | K1: Reporting To | L1: Category Code | M1: Designation Name | N1: Date Of Joining | O1: Phone | P1: E_ID | Q1: Mail
A2: 1 | B2: Shivangi | C2: Paras@123 | D2: Respiratory ICU | E2: INCIDENT REPORTER | F2: Paras HMRI Patna | G2: Patna | H2: ranishivangi9199@gmail.com | I2: 9199023328 | J2: PT-PA05897 | K2: Neha Mehta | L2: Nursing | M2: Staff Nurse | N2: 45281 | O2: =INDEX(Med!J:J,MATCH(Paras!I2,Med!J:J,0)) -> #N/A | P2: =INDEX(Med!B:B,MATCH(Paras!J2,Med!B:B,0)) -> #N/A | Q2: =INDEX(Med!K:K,MATCH(Paras!H2,Med!K:K,0)) -> #N/A
A3: 2 | B3: Divya Yadav | C3: Paras@123 | D3: Emergency | E3: INCIDENT REPORTER | F3: Paras HMRI Patna | G3: Patna | H3: dilipyadav199091@gmail.com | I3: 7905497275 | J3: PT-PA05899 | K3: Onkar Mani Tirpathi | L3: Nursing | M3: Sr. Staff Nurse | N3: 45282 | O3: =INDEX(Med!J:J,MATCH(Paras!I3,Med!J:J,0)) -> #N/A | P3: =INDEX(Med!B:B,MATCH(Paras!J3,Med!B:B,0)) -> #N/A | Q3: =INDEX(Med!K:K,MATCH(Paras!H3,Med!K:K,0)) -> #N/A
A4: 3 | B4: Priyasmita Chattapadhyay | C4: Paras@123 | D4: Guest Relations | E4: INCIDENT REPORTER | F4: Paras HMRI Patna | G4: Patna | H4: priyasmitactjee888@gmail.com | I4: 8240873293 | J4: PT-PA05901 | K4: Ramavtar Jangid | L4: Support | M4: Sr. Executive- Level 1 | N4: 45288 | O4: =INDEX(Med!J:J,MATCH(Paras!I4,Med!J:J,0)) -> 8240873293 | P4: =INDEX(Med!B:B,MATCH(Paras!J4,Med!B:B,0)) -> #N/A | Q4: =INDEX(Med!K:K,MATCH(Paras!H4,Med!K:K,0)) -> #N/A
A5: 4 | B5: Nishant singh | C5: Paras@123 | D5: Neurology | E5: INCIDENT REPORTER | F5: Paras HMRI Patna | G5: Patna | H5: nishantsingh19@gmail.com | I5: 7903950921 | J5: PT-PA05902 | K5: Manish Kumar | L5: Doctors | M5: DNB Primary - 1 | N5: 45288 | O5: =INDEX(Med!J:J,MATCH(Paras!I5,Med!J:J,0)) -> #N/A | P5: =INDEX(Med!B:B,MATCH(Paras!J5,Med!B:B,0)) -> #N/A | Q5: =INDEX(Med!K:K,MATCH(Paras!H5,Med!K:K,0)) -> #N/A
A6: 5 | B6: Sujay Ranjan | C6: Paras@123 | D6: Nephrology | E6: INCIDENT REPORTER | F6: Paras HMRI Patna | G6: Patna | H6: sujaynmch@gmail.com | I6: 9430559937 | J6: PT-PA05904 | K6: Manish Kumar | L6: Doctors | M6: DNB Primary - 1 | N6: 45293 | O6: =INDEX(Med!J:J,MATCH(Paras!I6,Med!J:J,0)) -> #N/A | P6: =INDEX(Med!B:B,MATCH(Paras!J6,Med!B:B,0)) -> #N/A | Q6: =INDEX(Med!K:K,MATCH(Paras!H6,Med!K:K,0)) -> #N/A
A7: 6 | B7: Prem Chandra Kumar | C7: Paras@123 | D7: Dispatch | E7: INCIDENT REPORTER | F7: Paras HMRI Patna | G7: Patna | H7: PREMPARASHMRI@GMAIL.COM | I7: 6202743641 | J7: PT-PAT-00035 | K7: Shailesh Mauar | L7: Administration | M7: Office Assistant- Level 1 | N7: 41426 | O7: =INDEX(Med!J:J,MATCH(Paras!I7,Med!J:J,0)) -> #N/A | P7: =INDEX(Med!B:B,MATCH(Paras!J7,Med!B:B,0)) -> #N/A | Q7: =INDEX(Med!K:K,MATCH(Paras!H7,Med!K:K,0)) -> #N/A
A8: 7 | B8: Abhishek | C8: Paras@123 | D8: Neurology | E8: INCIDENT REPORTER | F8: Paras HMRI Patna | G8: Patna | H8: drabhishek.kumar@parashospitals.com | I8: 9431432955 | J8: PT-PAT-00109 | K8: Anil Kumar | L8: Doctors | M8: Senior Consultant | N8: 41456 | O8: =INDEX(Med!J:J,MATCH(Paras!I8,Med!J:J,0)) -> #N/A | P8: =INDEX(Med!B:B,MATCH(Paras!J8,Med!B:B,0)) -> #N/A | Q8: =INDEX(Med!K:K,MATCH(Paras!H8,Med!K:K,0)) -> #N/A
A9: 8 | B9: Bineeta Sinha | C9: Paras@123 | D9: Clinical Pathology | E9: INCIDENT REPORTER | F9: Paras HMRI Patna | G9: Patna | H9: drbineeta.sinha@parashospitals.com | I9: 7858888175 | J9: PT-PAT-00110 | K9: Anil Kumar | L9: Doctors | M9: Principal Consultant | N9: 41456 | O9: =INDEX(Med!J:J,MATCH(Paras!I9,Med!J:J,0)) -> #N/A | P9: =INDEX(Med!B:B,MATCH(Paras!J9,Med!B:B,0)) -> #N/A | Q9: =INDEX(Med!K:K,MATCH(Paras!H9,Med!K:K,0)) -> #N/A
A10: 9 | B10: Masihullah | C10: Paras@123 | D10: MAMBS | E10: INCIDENT REPORTER | F10: Paras HMRI Patna | G10: Patna | H10: drmashiullah@parashospitals.com | I10: 9835848120 | J10: PT-PAT-00113 | K10: Manish Kumar | L10: Doctors | M10: Associate Director | N10: 41456 | O10: =INDEX(Med!J:J,MATCH(Paras!I10,Med!J:J,0)) -> #N/A | P10: =INDEX(Med!B:B,MATCH(Paras!J10,Med!B:B,0)) -> #N/A | Q10: =INDEX(Med!K:K,MATCH(Paras!H10,Med!K:K,0)) -> #N/A
A11: 10 | B11: Gautam Ram Babu Prasad | C11: Paras@123 | D11: Ortho Spine Surgery | E11: INCIDENT REPORTER | F11: Paras HMRI Patna | G11: Patna | H11: careforspine@yahoo.com | I11: 8877667722 | J11: PT-PAT-00122 | K11: Anil Kumar | L11: Revenue Generating Doctors | M11: Associate Director | N11: 41487 | O11: =INDEX(Med!J:J,MATCH(Paras!I11,Med!J:J,0)) -> #N/A | P11: =INDEX(Med!B:B,MATCH(Paras!J11,Med!B:B,0)) -> #N/A | Q11: =INDEX(Med!K:K,MATCH(Paras!H11,Med!K:K,0)) -> #N/A
A12: 11 | B12: Jibi Varghese | C12: Paras@123 | D12: Nursing Administration | E12: INCIDENT REPORTER | F12: Paras HMRI Patna | G12: Patna | H12: Jibijosejace@Gmail.Com | I12: 7654346060 | J12: PT-PAT-00152 | K12: Subhra Ghatak | L12: Nursing | M12: Manager | N12: 41457 | O12: =INDEX(Med!J:J,MATCH(Paras!I12,Med!J:J,0)) -> 7654346060 | P12: =INDEX(Med!B:B,MATCH(Paras!J12,Med!B:B,0)) -> PT-PAT-00152 | Q12: =INDEX(Med!K:K,MATCH(Paras!H12,Med!K:K,0)) -> #N/A
A13: 12 | B13: Vinod K Thakur | C13: Paras@123 | D13: Joint Replacement Surgery | E13: INCIDENT REPORTER | F13: Paras HMRI Patna | G13: Patna | H13: drvinodkrthakur@gmail.com | I13: 9431041154 | J13: PT-PAT-00197 | K13: Anil Kumar | L13: Revenue Generating Doctors | M13: Associate Director | N13: 41487 | O13: =INDEX(Med!J:J,MATCH(Paras!I13,Med!J:J,0)) -> #N/A | P13: =INDEX(Med!B:B,MATCH(Paras!J13,Med!B:B,0)) -> #N/A | Q13: =INDEX(Med!K:K,MATCH(Paras!H13,Med!K:K,0)) -> #N/A
... A39: 38 | B39: Ahmad Abdul Hai | C39: Paras@123 | D39: MAMBS | E39: INCIDENT REPORTER | F39: Paras HMRI Patna | G39: Patna | H39: draahai@parashospitals.com | I39: 9304972834 | J39: PT-PAT-00465 | K39: Anil Kumar | L39: Doctors | M39: Director | N39: 41487 | O39: =INDEX(Med!J:J,MATCH(Paras!I39,Med!J:J,0)) -> #N/A | P39: =INDEX(Med!B:B,MATCH(Paras!J39,Med!B:B,0)) -> #N/A | Q39: =INDEX(Med!K:K,MATCH(Paras!H39,Med!K:K,0)) -> #N/A
A40: 39 | B40: John Mukhopadhyay | C40: Paras@123 | D40: Joint Replacement Surgery | E40: INCIDENT REPORTER | F40: Paras HMRI Patna | G40: Patna | H40: drjhon@parashospitals.com | J40: PT-PAT-00466 | K40: Anil Kumar | L40: Revenue Generating Doctors | M40: Director | N40: 41487 | O40: =INDEX(Med!J:J,MATCH(Paras!I40,Med!J:J,0)) -> #N/A | P40: =INDEX(Med!B:B,MATCH(Paras!J40,Med!B:B,0)) -> #N/A | Q40: =INDEX(Med!K:K,MATCH(Paras!H40,Med!K:K,0)) -> #N/A
A41: 40 | B41: Rajiv Ranjan | C41: Paras@123 | D41: Paediatrics | E41: INCIDENT REPORTER | F41: Paras HMRI Patna | G41: Patna | H41: drrajivranjan@yahoo.com | I41: 9801835440 | J41: PT-PAT-00483 | K41: Anil Kumar | L41: Doctors | M41: Senior Consultant | N41: 41533 | O41: =INDEX(Med!J:J,MATCH(Paras!I41,Med!J:J,0)) -> #N/A | P41: =INDEX(Med!B:B,MATCH(Paras!J41,Med!B:B,0)) -> #N/A | Q41: =INDEX(Med!K:K,MATCH(Paras!H41,Med!K:K,0)) -> #N/A
A42: 41 | B42: Md. Moshirul Islam Khan | C42: Paras@123 | D42: General OT | E42: INCIDENT REPORTER | F42: Paras HMRI Patna | G42: Patna | H42: mikhan286@gmail.com | I42: 9308897408 | J42: PT-PAT-00564 | K42: Neha Singh | L42: Paramedics | M42: Sr. Technician - Level 1 | N42: 41557 | O42: =INDEX(Med!J:J,MATCH(Paras!I42,Med!J:J,0)) -> #N/A | P42: =INDEX(Med!B:B,MATCH(Paras!J42,Med!B:B,0)) -> #N/A | Q42: =INDEX(Med!K:K,MATCH(Paras!H42,Med!K:K,0)) -> #N/A
A43: 42 | B43: Anjani Mehra | C43: Paras@123 | D43: Neuro Surgical ICU | E43: INCIDENT REPORTER | F43: Paras HMRI Patna | G43: Patna | H43: dranjanimehra091@gmail.com | I43: 9507008008 | J43: PT-PAT-00698 | K43: Manish Kumar | L43: Doctors | M43: Attending Consultant | N43: 41628 | O43: =INDEX(Med!J:J,MATCH(Paras!I43,Med!J:J,0)) -> #N/A | P43: =INDEX(Med!B:B,MATCH(Paras!J43,Med!B:B,0)) -> #N/A | Q43: =INDEX(Med!K:K,MATCH(Paras!H43,Med!K:K,0)) -> #N/A
A44: 43 | B44: Ravi Bhaskar | C44: Paras@123 | D44: IP Pharmacy | E44: INCIDENT REPORTER | F44: Paras HMRI Patna | G44: Patna | H44: acmailmetest@gmail.com | I44: 7004320579 | J44: PT-PAT-00714 | K44: Arbind Prasad | L44: Paramedics | M44: Sr. Pharmacist - Level 1 | N44: 41575 | O44: =INDEX(Med!J:J,MATCH(Paras!I44,Med!J:J,0)) -> #N/A | P44: =INDEX(Med!B:B,MATCH(Paras!J44,Med!B:B,0)) -> #N/A | Q44: =INDEX(Med!K:K,MATCH(Paras!H44,Med!K:K,0)) -> #N/A
A45: 44 | B45: Avinash Kumar Singh | C45: Paras@123 | D45: Haemato Oncology & BMT | E45: INCIDENT REPORTER | F45: Paras HMRI Patna | G45: Patna | H45: avanish.kumar@parashospitals.com | I45: 9960945860 | J45: PT-PAT-00727 | K45: Anil Kumar | L45: Revenue Generating Doctors | M45: Director | N45: 41641 | O45: =INDEX(Med!J:J,MATCH(Paras!I45,Med!J:J,0)) -> #N/A | P45: =INDEX(Med!B:B,MATCH(Paras!J45,Med!B:B,0)) -> #N/A | Q45: =INDEX(Med!K:K,MATCH(Paras!H45,Med!K:K,0)) -> #N/A
A46: 45 | B46: Mazharul Haque | C46: Paras@123 | D46: Bio Chemistry | E46: INCIDENT REPORTER | F46: Paras HMRI Patna | G46: Patna | H46: mazharulhaque71@gmail.com | I46: 7903281806 | J46: PT-PAT-00729 | K46: Ravi Ranjan Kumar | L46: Paramedics | M46: Sr. Technician - Level 2 | N46: 41641 | O46: =INDEX(Med!J:J,MATCH(Paras!I46,Med!J:J,0)) -> #N/A | P46: =INDEX(Med!B:B,MATCH(Paras!J46,Med!B:B,0)) -> #N/A | Q46: =INDEX(Med!K:K,MATCH(Paras!H46,Med!K:K,0)) -> #N/A
A47: 46 | B47: Sushil Kumar | C47: Paras@123 | D47: Endoscopy | E47: INCIDENT REPORTER | F47: Paras HMRI Patna | G47: Patna | H47: kumarsunil1111@gmail.com | I47: 9955569687 | J47: PT-PAT-00768 | K47: Manish Kumar | L47: Paramedics | M47: Technician - Level 1 | N47: 41655 | O47: =INDEX(Med!J:J,MATCH(Paras!I47,Med!J:J,0)) -> #N/A | P47: =INDEX(Med!B:B,MATCH(Paras!J47,Med!B:B,0)) -> #N/A | Q47: =INDEX(Med!K:K,MATCH(Paras!H47,Med!K:K,0)) -> #N/A
A48: 47 | B48: Rufina Kispotta | C48: Paras@123 | D48: CCU | E48: INCIDENT REPORTER | F48: Paras HMRI Patna | G48: Patna | H48: Rufinakispotta074@Gmail.Com | I48: 7781866326 | J48: PT-PAT-00788 | K48: Archana Chandra | L48: Nursing | M48: Sr. Staff Nurse | N48: 41663 | O48: =INDEX(Med!J:J,MATCH(Paras!I48,Med!J:J,0)) -> 7781866326 | P48: =INDEX(Med!B:B,MATCH(Paras!J48,Med!B:B,0)) -> PT-PAT-00788 | Q48: =INDEX(Med!K:K,MATCH(Paras!H48,Med!K:K,0)) -> #N/A
A49: 48 | B49: Md. Khurshid Alam | C49: Paras@123 | D49: General OT | E49: INCIDENT REPORTER | F49: Paras HMRI Patna | G49: Patna | H49: khurshid.alam2010@yahoo.com | I49: 9155581676 | J49: PT-PAT-00937 | K49: Neha Singh | L49: Paramedics | M49: Senior Supervisor | N49: 41739 | O49: =INDEX(Med!J:J,MATCH(Paras!I49,Med!J:J,0)) -> #N/A | P49: =INDEX(Med!B:B,MATCH(Paras!J49,Med!B:B,0)) -> #N/A | Q49: =INDEX(Med!K:K,MATCH(Paras!H49,Med!K:K,0)) -> #N/A
A50: 49 | B50: Satish Srivastava | C50: Paras@123 | D50: Coordinator Pool | E50: INCIDENT REPORTER | F50: Paras HMRI Patna | G50: Patna | H50: satish.bstdc@gmail.com | I50: 8002150150 | J50: PT-PAT-00950 | K50: Ramavtar Jangid | L50: Administration | M50: Deputy Manager | N50: 41744 | O50: =INDEX(Med!J:J,MATCH(Paras!I50,Med!J:J,0)) -> #N/A | P50: =INDEX(Med!B:B,MATCH(Paras!J50,Med!B:B,0)) -> #N/A | Q50: =INDEX(Med!K:K,MATCH(Paras!H50,Med!K:K,0)) -> #N/A
A51: 50 | B51: CHANDAN KUMAR JHA | C51: Paras@123 | D51: Blood Bank | E51: INCIDENT REPORTER | F51: Paras HMRI Patna | G51: Patna | H51: CANDANJHA1985@GMAIL.COM | I51: 6201482174 | J51: PT-PAT-01042 | K51: Syed Md. Shamsheer Ahmad | L51: Paramedics | M51: Sr. Technician - Level 1 | N51: 41792 | O51: =INDEX(Med!J:J,MATCH(Paras!I51,Med!J:J,0)) -> #N/A | P51: =INDEX(Med!B:B,MATCH(Paras!J51,Med!B:B,0)) -> #N/A | Q51: =INDEX(Med!K:K,MATCH(Paras!H51,Med!K:K,0)) -> #N/A
A52: 51 | B52: Amresh Kumar | C52: Paras@123 | D52: Neurology | E52: INCIDENT REPORTER | F52: Paras HMRI Patna | G52: Patna | H52: amreshkumar5186@gmail.com | I52: 7766021111 | J52: PT-PAT-01134 | K52: Manish Kumar | L52: Doctors | M52: Senior Medical Officer | N52: 41848 | O52: =INDEX(Med!J:J,MATCH(Paras!I52,Med!J:J,0)) -> #N/A | P52: =INDEX(Med!B:B,MATCH(Paras!J52,Med!B:B,0)) -> #N/A | Q52: =INDEX(Med!K:K,MATCH(Paras!H52,Med!K:K,0)) -> #N/A
... A318: 317 | B318: Vivek Kumar | C318: Paras@123 | D318: Blood Bank | E318: INCIDENT REPORTER | F318: Paras HMRI Patna | G318: Patna | H318: VIVEKLUMAR012796@GMAIL.COM | I318: 8227957463 | J318: PT-PAT-06055 | K318: Syed Md. Shamsheer Ahmad | L318: Paramedics | M318: Technician - Level 1 | N318: 45425 | O318: =INDEX(Med!J:J,MATCH(Paras!I318,Med!J:J,0)) -> #N/A | P318: =INDEX(Med!B:B,MATCH(Paras!J318,Med!B:B,0)) -> #N/A | Q318: =INDEX(Med!K:K,MATCH(Paras!H318,Med!K:K,0)) -> #N/A
A319: 318 | B319: Anil Kumar | C319: Paras@123 | D319: Hospital Operations | E319: INCIDENT REPORTER | F319: Paras HMRI Patna | G319: Patna | H319: kumar.anil@parashospitals.com | I319: 9950067666 | J319: PT-PAT-06060 | L319: Administration | M319: Zonal Director | N319: 45434 | O319: =INDEX(Med!J:J,MATCH(Paras!I319,Med!J:J,0)) -> #N/A | P319: =INDEX(Med!B:B,MATCH(Paras!J319,Med!B:B,0)) -> #N/A | Q319: =INDEX(Med!K:K,MATCH(Paras!H319,Med!K:K,0)) -> #N/A
A320: 319 | B320: Neeraj Sinha | C320: Paras@123 | D320: Endocrinology | E320: INCIDENT REPORTER | F320: Paras HMRI Patna | G320: Patna | H320: dr.neerajsinha@gmail.com | I320: 9748718138 | J320: PT-PAT-06063 | K320: Anil Kumar | L320: Revenue Generating Doctors | M320: Senior Consultant | N320: 45444 | O320: =INDEX(Med!J:J,MATCH(Paras!I320,Med!J:J,0)) -> #N/A | P320: =INDEX(Med!B:B,MATCH(Paras!J320,Med!B:B,0)) -> #N/A | Q320: =INDEX(Med!K:K,MATCH(Paras!H320,Med!K:K,0)) -> #N/A
A321: 320 | B321: Ramavtar Jangid | C321: Paras@123 | D321: Front Office | E321: INCIDENT REPORTER | F321: Paras HMRI Patna | G321: Patna | H321: ramavtar.jangid@parashospitals.com | I321: 9587112029 | J321: PT-PAT-06064 | K321: Anil Kumar | L321: Support | M321: General Manager | N321: 45476 | O321: =INDEX(Med!J:J,MATCH(Paras!I321,Med!J:J,0)) -> #N/A | P321: =INDEX(Med!B:B,MATCH(Paras!J321,Med!B:B,0)) -> #N/A | Q321: =INDEX(Med!K:K,MATCH(Paras!H321,Med!K:K,0)) -> #N/A
A322: 321 | B322: Payal Pandey | C322: Paras@123 | D322: Sales & Marketing | E322: INCIDENT REPORTER | F322: Paras HMRI Patna | G322: Patna | H322: payal.pandey@parashospitals.com | I322: 7091819078 | J322: PT-PAT-06065 | K322: Rohit Kumar | L322: Administration | M322: Assistant Manager | N322: 45476 | O322: =INDEX(Med!J:J,MATCH(Paras!I322,Med!J:J,0)) -> #N/A | P322: =INDEX(Med!B:B,MATCH(Paras!J322,Med!B:B,0)) -> #N/A | Q322: =INDEX(Med!K:K,MATCH(Paras!H322,Med!K:K,0)) -> #N/A
A323: 322 | B323: Shivam Kumar | C323: Paras@123 | D323: Domestic Sales | E323: INCIDENT REPORTER | F323: Paras HMRI Patna | G323: Patna | H323: shivamsingh22295@gmail.com | I323: 7908835002 | J323: PT-PAT-06066 | K323: Rohit Kumar | L323: Administration | M323: Manager | N323: 45476 | O323: =INDEX(Med!J:J,MATCH(Paras!I323,Med!J:J,0)) -> #N/A | P323: =INDEX(Med!B:B,MATCH(Paras!J323,Med!B:B,0)) -> #N/A | Q323: =INDEX(Med!K:K,MATCH(Paras!H323,Med!K:K,0)) -> #N/A
A324: 323 | B324: Ranu Kumar | C324: Paras@123 | D324: Domestic Sales | E324: INCIDENT REPORTER | F324: Paras HMRI Patna | G324: Patna | H324: ranubhardwaj2846@gmail.com | I324: 9905769823 | J324: PT-PAT-06067 | K324: Rohit Kumar | L324: Administration | M324: Assistant Manager | N324: 45477 | O324: =INDEX(Med!J:J,MATCH(Paras!I324,Med!J:J,0)) -> #N/A | P324: =INDEX(Med!B:B,MATCH(Paras!J324,Med!B:B,0)) -> #N/A | Q324: =INDEX(Med!K:K,MATCH(Paras!H324,Med!K:K,0)) -> #N/A
A325: 324 | B325: Vishal Anand | C325: Paras@123 | D325: IP Pharmacy | E325: INCIDENT REPORTER | F325: Paras HMRI Patna | G325: Patna | H325: vishalanand2222@gmail.com | I325: 6205754459 | J325: PT-PAT-06068 | K325: Arbind Prasad | L325: Paramedics | M325: Sr. Pharmacist - Level 1 | N325: 45478 | O325: =INDEX(Med!J:J,MATCH(Paras!I325,Med!J:J,0)) -> #N/A | P325: =INDEX(Med!B:B,MATCH(Paras!J325,Med!B:B,0)) -> #N/A | Q325: =INDEX(Med!K:K,MATCH(Paras!H325,Med!K:K,0)) -> #N/A
A326: 325 | B326: Ratnesh Raj | C326: Paras@123 | D326: OP Pharmacy | E326: INCIDENT REPORTER | F326: Paras HMRI Patna | G326: Patna | H326: rajratnesh89@gmail.com | I326: 9973044800 | J326: PT-PAT-06069 | K326: Arbind Prasad | L326: Paramedics | M326: Pharmacist - Level 1 | N326: 45478 | O326: =INDEX(Med!J:J,MATCH(Paras!I326,Med!J:J,0)) -> #N/A | P326: =INDEX(Med!B:B,MATCH(Paras!J326,Med!B:B,0)) -> #N/A | Q326: =INDEX(Med!K:K,MATCH(Paras!H326,Med!K:K,0)) -> #N/A
A327: 326 | B327: Pallab Pati | C327: Paras@123 | D327: Radiation Oncology | E327: INCIDENT REPORTER | F327: Paras HMRI Patna | G327: Patna | H327: pallabpati8@gmail.com | I327: 8250667262 | J327: PT-PAT-06074 | K327: Jesu Jackin Lawrence | L327: Paramedics | M327: Sr. Technician - Level 1 | N327: 45495 | O327: =INDEX(Med!J:J,MATCH(Paras!I327,Med!J:J,0)) -> #N/A | P327: =INDEX(Med!B:B,MATCH(Paras!J327,Med!B:B,0)) -> #N/A | Q327: =INDEX(Med!K:K,MATCH(Paras!H327,Med!K:K,0)) -> #N/A
A328: 327 | B328: Harendra Kumar Singh | C328: Paras@123 | D328: Billing | E328: INCIDENT REPORTER | F328: Paras HMRI Patna | G328: Patna | H328: harendrakumar@singh@parashospitals.com | I328: 9811404042 | J328: PT-PAT-06078 | K328: Ramavtar Jangid | L328: Administration | M328: Sr. Manager | N328: 45499 | O328: =INDEX(Med!J:J,MATCH(Paras!I328,Med!J:J,0)) -> #N/A | P328: =INDEX(Med!B:B,MATCH(Paras!J328,Med!B:B,0)) -> #N/A | Q328: =INDEX(Med!K:K,MATCH(Paras!H328,Med!K:K,0)) -> #N/A
A329: 328 | B329: Neeraj Kumar | C329: Paras@123 | D329: Accounts | E329: INCIDENT REPORTER | F329: Paras HMRI Patna | G329: Patna | H329: neeraj.kumar@parashospitals.com | I329: 9810870948 | J329: PT-PAT-06079 | K329: Anil Kumar | L329: Administration | M329: Deputy General Manager | N329: 45500 | O329: =INDEX(Med!J:J,MATCH(Paras!I329,Med!J:J,0)) -> #N/A | P329: =INDEX(Med!B:B,MATCH(Paras!J329,Med!B:B,0)) -> PT-PAT-06079 | Q329: =INDEX(Med!K:K,MATCH(Paras!H329,Med!K:K,0)) -> neeraj.kumar@parashospitals.com
A330: 329 | B330: Firoj Alam | C330: Paras@123 | D330: Medical Surgical Ward | E330: INCIDENT REPORTER | F330: Paras HMRI Patna | G330: Patna | H330: Falam2688@Gmail.Com | I330: 7033067294 | J330: PT-PAT-06086 | K330: Minakshi Pandey | L330: Nursing | M330: Staff Nurse | N330: 45502 | O330: =INDEX(Med!J:J,MATCH(Paras!I330,Med!J:J,0)) -> #N/A | P330: =INDEX(Med!B:B,MATCH(Paras!J330,Med!B:B,0)) -> #N/A | Q330: =INDEX(Med!K:K,MATCH(Paras!H330,Med!K:K,0)) -> #N/A
A331: 330 | B331: Minakshi Pandey | C331: Paras@123 | D331: Medical Surgical Ward | E331: INCIDENT REPORTER | F331: Paras HMRI Patna | G331: Patna | H331: meenakshipandey73555@gmail.com | I331: 9151755620 | J331: PT-PAT-06087 | K331: Jibi Varghese | L331: Nursing | M331: Ward Incharge | N331: 45504 | O331: =INDEX(Med!J:J,MATCH(Paras!I331,Med!J:J,0)) -> #N/A | P331: =INDEX(Med!B:B,MATCH(Paras!J331,Med!B:B,0)) -> #N/A | Q331: =INDEX(Med!K:K,MATCH(Paras!H331,Med!K:K,0)) -> #N/A
... A614: 613 | B614: Ramli Sastiya | C614: Paras@123 | D614: Medical Surgical Ward | E614: INCIDENT REPORTER | F614: Paras HMRI Patna | G614: Patna | H614: ramlisastiya21@gmail.com | I614: 7691920490 | J614: PT-PAT-06837 | K614: Anima Balbandi | L614: Nursing | M614: Staff Nurse | N614: 45953 | O614: =INDEX(Med!J:J,MATCH(Paras!I614,Med!J:J,0)) -> #N/A | P614: =INDEX(Med!B:B,MATCH(Paras!J614,Med!B:B,0)) -> #N/A | Q614: =INDEX(Med!K:K,MATCH(Paras!H614,Med!K:K,0)) -> #N/A
A615: 614 | B615: Harshit Anand | C615: Paras@123 | D615: Coordinator Pool | E615: INCIDENT REPORTER | F615: Paras HMRI Patna | G615: Patna | I615: 9006455422 | J615: PT-PAT-06842 | K615: Ramavtar Jangid | L615: Administration | M615: Executive- Level 1 | N615: 45960 | O615: =INDEX(Med!J:J,MATCH(Paras!I615,Med!J:J,0)) -> #N/A | P615: =INDEX(Med!B:B,MATCH(Paras!J615,Med!B:B,0)) -> #N/A | Q615: =INDEX(Med!K:K,MATCH(Paras!H615,Med!K:K,0))
A616: 615 | B616: Anandita Namita Mundu | C616: Paras@123 | D616: Medical Surgical Ward | E616: INCIDENT REPORTER | F616: Paras HMRI Patna | G616: Patna | H616: ananditanamita@gmail.com | I616: 8340749531 | J616: PT-PAT-06845 | K616: Jibi Varghese | L616: Nursing | M616: Sr. Staff Nurse | N616: 45964 | O616: =INDEX(Med!J:J,MATCH(Paras!I616,Med!J:J,0)) -> #N/A | P616: =INDEX(Med!B:B,MATCH(Paras!J616,Med!B:B,0)) -> #N/A | Q616: =INDEX(Med!K:K,MATCH(Paras!H616,Med!K:K,0)) -> #N/A
A617: 616 | B617: Samar Jeet | C617: Paras@123 | D617: Supply chain Management | E617: INCIDENT REPORTER | F617: Paras HMRI Patna | G617: Patna | I617: 8826362517 | J617: PT-PAT-06850 | K617: Vikrant Singh | L617: Administration | M617: Sr. Executive- Level 1 | N617: 45965 | O617: =INDEX(Med!J:J,MATCH(Paras!I617,Med!J:J,0)) -> #N/A | P617: =INDEX(Med!B:B,MATCH(Paras!J617,Med!B:B,0)) -> #N/A | Q617: =INDEX(Med!K:K,MATCH(Paras!H617,Med!K:K,0))
A618: 617 | B618: Ratnanjali | C618: Paras@123 | D618: Non Invasive Cardiology | E618: INCIDENT REPORTER | F618: Paras HMRI Patna | G618: Patna | I618: 8303517880 | J618: PT-PAT-06851 | K618: Manish Kumar | L618: Paramedics | M618: Technician - Level 1 | N618: 45967 | O618: =INDEX(Med!J:J,MATCH(Paras!I618,Med!J:J,0)) -> #N/A | P618: =INDEX(Med!B:B,MATCH(Paras!J618,Med!B:B,0)) -> #N/A | Q618: =INDEX(Med!K:K,MATCH(Paras!H618,Med!K:K,0))
A619: 618 | B619: Ritu Raj | C619: Paras@123 | D619: Dialysis Unit | E619: INCIDENT REPORTER | F619: Paras HMRI Patna | G619: Patna | I619: 7759904856 | J619: PT-PAT-06853 | K619: Dalip Kumar | L619: Paramedics | M619: Sr. Technician - Level 1 | N619: 45968 | O619: =INDEX(Med!J:J,MATCH(Paras!I619,Med!J:J,0)) -> #N/A | P619: =INDEX(Med!B:B,MATCH(Paras!J619,Med!B:B,0)) -> #N/A | Q619: =INDEX(Med!K:K,MATCH(Paras!H619,Med!K:K,0))
A620: 619 | B620: Rambabu Kumar | C620: Paras@123 | D620: Admission | E620: INCIDENT REPORTER | F620: Paras HMRI Patna | G620: Patna | I620: 7654663749 | J620: PT-PAT-06857 | K620: Ramavtar Jangid | L620: Support | M620: Coordinator- Level 1 | N620: 45971 | O620: =INDEX(Med!J:J,MATCH(Paras!I620,Med!J:J,0)) -> #N/A | P620: =INDEX(Med!B:B,MATCH(Paras!J620,Med!B:B,0)) -> #N/A | Q620: =INDEX(Med!K:K,MATCH(Paras!H620,Med!K:K,0))
A621: 620 | B621: Anjali Kumari | C621: Paras@123 | D621: Medical Surgical Ward | E621: INCIDENT REPORTER | F621: Paras HMRI Patna | G621: Patna | I621: 6204251774 | J621: PT-PAT-06858 | K621: Anima Balbandi | L621: Nursing | M621: Staff Nurse | N621: 45971 | O621: =INDEX(Med!J:J,MATCH(Paras!I621,Med!J:J,0)) -> #N/A | P621: =INDEX(Med!B:B,MATCH(Paras!J621,Med!B:B,0)) -> #N/A | Q621: =INDEX(Med!K:K,MATCH(Paras!H621,Med!K:K,0))
A622: 621 | B622: Aarti | C622: Paras@123 | D622: OP Billing | E622: INCIDENT REPORTER | F622: Paras HMRI Patna | G622: Patna | I622: 8802400136 | J622: PT-PAT-06859 | K622: Ramavtar Jangid | L622: Support | M622: Executive- Level 1 | N622: 45971 | O622: =INDEX(Med!J:J,MATCH(Paras!I622,Med!J:J,0)) -> #N/A | P622: =INDEX(Med!B:B,MATCH(Paras!J622,Med!B:B,0)) -> #N/A | Q622: =INDEX(Med!K:K,MATCH(Paras!H622,Med!K:K,0))
A623: 622 | B623: Kalani Kumari | C623: Paras@123 | D623: Respiratory ICU | E623: INCIDENT REPORTER | F623: Paras HMRI Patna | G623: Patna | I623: 9523229781 | J623: PT-PAT-06860 | K623: Neha Mehta | L623: Nursing | M623: Staff Nurse | N623: 45971 | O623: =INDEX(Med!J:J,MATCH(Paras!I623,Med!J:J,0)) -> #N/A | P623: =INDEX(Med!B:B,MATCH(Paras!J623,Med!B:B,0)) -> #N/A | Q623: =INDEX(Med!K:K,MATCH(Paras!H623,Med!K:K,0))
A624: 623 | B624: Salim Ahmad Ansari | C624: Paras@123 | D624: Pre & Post Operations | E624: INCIDENT REPORTER | F624: Paras HMRI Patna | G624: Patna | I624: 8969867728 | J624: PT-PAT-06863 | K624: Manisha Kumari | L624: Nursing | M624: Staff Nurse | N624: 45972 | O624: =INDEX(Med!J:J,MATCH(Paras!I624,Med!J:J,0)) -> #N/A | P624: =INDEX(Med!B:B,MATCH(Paras!J624,Med!B:B,0)) -> #N/A | Q624: =INDEX(Med!K:K,MATCH(Paras!H624,Med!K:K,0))
A625: 624 | B625: Simran Muskan | C625: Paras@123 | D625: OP Billing | E625: INCIDENT REPORTER | F625: Paras HMRI Patna | G625: Patna | I625: 8102228393 | J625: PT-PAT-06864 | K625: Ramavtar Jangid | L625: Support | M625: Executive- Level 1 | N625: 45973 | O625: =INDEX(Med!J:J,MATCH(Paras!I625,Med!J:J,0)) -> #N/A | P625: =INDEX(Med!B:B,MATCH(Paras!J625,Med!B:B,0)) -> #N/A | Q625: =INDEX(Med!K:K,MATCH(Paras!H625,Med!K:K,0))
A626: 625 | B626: Muskan Kumari | C626: Paras@123 | D626: Coordinator Pool | E626: INCIDENT REPORTER | F626: Paras HMRI Patna | G626: Patna | I626: 6203828120 | J626: PT-PAT-06865 | K626: Ramavtar Jangid | L626: Administration | M626: Executive- Level 1 | N626: 45973 | O626: =INDEX(Med!J:J,MATCH(Paras!I626,Med!J:J,0)) -> #N/A | P626: =INDEX(Med!B:B,MATCH(Paras!J626,Med!B:B,0)) -> #N/A | Q626: =INDEX(Med!K:K,MATCH(Paras!H626,Med!K:K,0))
A627: 626 | B627: Ankit kumar | C627: Paras@123 | D627: Camp Services | E627: INCIDENT REPORTER | F627: Paras HMRI Patna | G627: Patna | I627: 6204799745 | J627: PT-PAT-06867 | K627: Rohit Kumar | L627: Administration | M627: Executive- Level 1 | N627: 45973 | O627: =INDEX(Med!J:J,MATCH(Paras!I627,Med!J:J,0)) -> #N/A | P627: =INDEX(Med!B:B,MATCH(Paras!J627,Med!B:B,0)) -> #N/A | Q627: =INDEX(Med!K:K,MATCH(Paras!H627,Med!K:K,0))
A628: 627 | B628: Rupa Mehata | C628: Paras@123 | D628: Medical Surgical Ward | E628: INCIDENT REPORTER | F628: Paras HMRI Patna | G628: Patna | I628: 8789218840 | J628: PT-PAT-06868 | K628: Minakshi Pandey | L628: Nursing | M628: Staff Nurse | N628: 45974 | O628: =INDEX(Med!J:J,MATCH(Paras!I628,Med!J:J,0)) -> #N/A | P628: =INDEX(Med!B:B,MATCH(Paras!J628,Med!B:B,0)) -> #N/A | Q628: =INDEX(Med!K:K,MATCH(Paras!H628,Med!K:K,0))
A629: 628 | B629: Pankaj Kumar | C629: Paras@123 | D629: OP Billing | E629: INCIDENT REPORTER | F629: Paras HMRI Patna | G629: Patna | H629: pankajkumarm930@gmail.com | I629: 8002665369 | J629: PT-PAT-06869 | K629: Ramavtar Jangid | L629: Support | M629: Executive- Level 1 | N629: 45974 | O629: =INDEX(Med!J:J,MATCH(Paras!I629,Med!J:J,0)) -> #N/A | P629: =INDEX(Med!B:B,MATCH(Paras!J629,Med!B:B,0)) -> #N/A | Q629: =INDEX(Med!K:K,MATCH(Paras!H629,Med!K:K,0)) -> #N/A
A630: 629 | B630: Kartavya Rai | C630: Paras@123 | D630: Medical Record Room | E630: INCIDENT REPORTER | F630: Paras HMRI Patna | G630: Patna | I630: 9341117920 | J630: PT-PAT-06871 | K630: Harendra Kumar Divakar | L630: Administration | M630: Executive- Level 1 | N630: 45974 | O630: =INDEX(Med!J:J,MATCH(Paras!I630,Med!J:J,0)) -> #N/A | P630: =INDEX(Med!B:B,MATCH(Paras!J630,Med!B:B,0)) -> #N/A | Q630: =INDEX(Med!K:K,MATCH(Paras!H630,Med!K:K,0))
A631: 630 | B631: Ankit Kumar Yadav | C631: Paras@123 | D631: Dialysis Unit | E631: INCIDENT REPORTER | F631: Paras HMRI Patna | G631: Patna | I631: 8210680967 | J631: PT-PAT-06872 | K631: Dalip Kumar | L631: Paramedics | M631: Technician - Level 1 | N631: 45974 | O631: =INDEX(Med!J:J,MATCH(Paras!I631,Med!J:J,0)) -> #N/A | P631: =INDEX(Med!B:B,MATCH(Paras!J631,Med!B:B,0)) -> #N/A | Q631: =INDEX(Med!K:K,MATCH(Paras!H631,Med!K:K,0))
A632: 631 | B632: Manisha Ranjan | C632: Paras@123 | D632: General OT | E632: INCIDENT REPORTER | F632: Paras HMRI Patna | G632: Patna | I632: 7273962254 | J632: PT-PAT-06873 | K632: Neha Singh | L632: Nursing | M632: Staff Nurse | N632: 45975 | O632: =INDEX(Med!J:J,MATCH(Paras!I632,Med!J:J,0)) -> #N/A | P632: =INDEX(Med!B:B,MATCH(Paras!J632,Med!B:B,0)) -> #N/A | Q632: =INDEX(Med!K:K,MATCH(Paras!H632,Med!K:K,0))
A633: 632 | B633: Aditya Kumar | C633: Paras@123 | D633: Pre & Post Operations | E633: INCIDENT REPORTER | F633: Paras HMRI Patna | G633: Patna | I633: 7033124840 | J633: PT-PAT-06874 | K633: Manisha Kumari | L633: Nursing | M633: Staff Nurse | N633: 45975 | O633: =INDEX(Med!J:J,MATCH(Paras!I633,Med!J:J,0)) -> #N/A | P633: =INDEX(Med!B:B,MATCH(Paras!J633,Med!B:B,0)) -> #N/A | Q633: =INDEX(Med!K:K,MATCH(Paras!H633,Med!K:K,0))
A634: 633 | B634: Zakeer Hussain | C634: Paras@123 | D634: Medical Surgical Ward | E634: INCIDENT REPORTER | F634: Paras HMRI Patna | G634: Patna | I634: 7091292657 | J634: PT-PAT-06875 | K634: Rinku Kumari | L634: Nursing | M634: Staff Nurse | N634: 45976 | O634: =INDEX(Med!J:J,MATCH(Paras!I634,Med!J:J,0)) -> #N/A | P634: =INDEX(Med!B:B,MATCH(Paras!J634,Med!B:B,0)) -> #N/A | Q634: =INDEX(Med!K:K,MATCH(Paras!H634,Med!K:K,0))
A635: 634 | B635: Stuti Kumari | C635: Paras@123 | D635: Neuro Surgical ICU | E635: INCIDENT REPORTER | F635: Paras HMRI Patna | G635: Patna | H635: stutikumari090@gmail.com | I635: 7762860341 | J635: PT-PAT-06876 | K635: Tannya Yadav | L635: Nursing | M635: Staff Nurse | N635: 45978 | O635: =INDEX(Med!J:J,MATCH(Paras!I635,Med!J:J,0)) -> #N/A | P635: =INDEX(Med!B:B,MATCH(Paras!J635,Med!B:B,0)) -> #N/A | Q635: =INDEX(Med!K:K,MATCH(Paras!H635,Med!K:K,0)) -> #N/A
A636: 635 | B636: Shashi Kant Sharma | C636: Paras@123 | D636: Information Technology | E636: INCIDENT REPORTER | F636: Paras HMRI Patna | G636: Patna | I636: 9852720608 | J636: PT-PAT-06878 | K636: Krishna Kumar | L636: Support | M636: Sr. Executive- Level 1 | N636: 45978 | O636: =INDEX(Med!J:J,MATCH(Paras!I636,Med!J:J,0)) -> #N/A | P636: =INDEX(Med!B:B,MATCH(Paras!J636,Med!B:B,0)) -> #N/A | Q636: =INDEX(Med!K:K,MATCH(Paras!H636,Med!K:K,0))
A637: 636 | B637: Santosh Kumar | C637: Paras@123 | D637: Cardiothoracic and Vascular Surgery | E637: INCIDENT REPORTER | F637: Paras HMRI Patna | G637: Patna | I637: 9136743734 | J637: PT-PAT-06879 | K637: Chandan Kumar | L637: Revenue Generating Doctors | M637: Attending Consultant | N637: 45978 | O637: =INDEX(Med!J:J,MATCH(Paras!I637,Med!J:J,0)) -> #N/A | P637: =INDEX(Med!B:B,MATCH(Paras!J637,Med!B:B,0)) -> #N/A | Q637: =INDEX(Med!K:K,MATCH(Paras!H637,Med!K:K,0))
A638: 637 | B638: Md Qamar Raza | C638: Paras@123 | D638: Medical Surgical Ward | E638: INCIDENT REPORTER | F638: Paras HMRI Patna | G638: Patna | I638: 7519527786 | J638: PT-PAT-06880 | K638: Punam Soren | L638: Nursing | M638: Staff Nurse | N638: 45978 | O638: =INDEX(Med!J:J,MATCH(Paras!I638,Med!J:J,0)) -> #N/A | P638: =INDEX(Med!B:B,MATCH(Paras!J638,Med!B:B,0)) -> #N/A | Q638: =INDEX(Med!K:K,MATCH(Paras!H638,Med!K:K,0))
A639: 638 | B639: Rajeev Ranjan | C639: Paras@123 | D639: Billing | E639: INCIDENT REPORTER | F639: Paras HMRI Patna | G639: Patna | I639: 6201729545 | J639: PT-PAT-06881 | K639: Harendra Kumar Singh | L639: Administration | M639: Sr. Executive- Level 1 | N639: 45978 | O639: =INDEX(Med!J:J,MATCH(Paras!I639,Med!J:J,0)) -> #N/A | P639: =INDEX(Med!B:B,MATCH(Paras!J639,Med!B:B,0)) -> #N/A | Q639: =INDEX(Med!K:K,MATCH(Paras!H639,Med!K:K,0))
A640: 639 | B640: Md Asif Iqbal | C640: Paras@123 | D640: Billing | E640: INCIDENT REPORTER | F640: Paras HMRI Patna | G640: Patna | I640: 9113149793 | J640: PT-PAT-06882 | K640: Harendra Kumar Singh | L640: Administration | M640: Sr. Executive- Level 1 | N640: 45978 | O640: =INDEX(Med!J:J,MATCH(Paras!I640,Med!J:J,0)) -> #N/A | P640: =INDEX(Med!B:B,MATCH(Paras!J640,Med!B:B,0)) -> #N/A | Q640: =INDEX(Med!K:K,MATCH(Paras!H640,Med!K:K,0))
A641: 640 | B641: Sahbe Alam | C641: Paras@123 | D641: Respiratory ICU | E641: INCIDENT REPORTER | F641: Paras HMRI Patna | G641: Patna | I641: 7091697050 | J641: PT-PAT-06883 | K641: Neha Mehta | L641: Nursing | M641: Staff Nurse | N641: 45978 | O641: =INDEX(Med!J:J,MATCH(Paras!I641,Med!J:J,0)) -> #N/A | P641: =INDEX(Med!B:B,MATCH(Paras!J641,Med!B:B,0)) -> #N/A | Q641: =INDEX(Med!K:K,MATCH(Paras!H641,Med!K:K,0))
A642: 641 | B642: Rajeev Kumar | C642: Paras@123 | D642: OP Billing | E642: INCIDENT REPORTER | F642: Paras HMRI Patna | G642: Patna | I642: 9570873872 | J642: PT-PAT-06884 | K642: Ramavtar Jangid | L642: Support | M642: Executive- Level 1 | N642: 45978 | O642: =INDEX(Med!J:J,MATCH(Paras!I642,Med!J:J,0)) -> #N/A | P642: =INDEX(Med!B:B,MATCH(Paras!J642,Med!B:B,0)) -> #N/A | Q642: =INDEX(Med!K:K,MATCH(Paras!H642,Med!K:K,0))
A643: 642 | B643: Deepak Kumar | C643: Paras@123 | D643: Emergency | E643: INCIDENT REPORTER | F643: Paras HMRI Patna | G643: Patna | I643: 7644075615 | J643: PT-PAT-06886 | K643: Onkar Mani Tirpathi | L643: Nursing | M643: Staff Nurse | N643: 45979 | O643: =INDEX(Med!J:J,MATCH(Paras!I643,Med!J:J,0)) -> #N/A | P643: =INDEX(Med!B:B,MATCH(Paras!J643,Med!B:B,0)) -> #N/A | Q643: =INDEX(Med!K:K,MATCH(Paras!H643,Med!K:K,0))
A644: 643 | B644: Himanshu Ray | C644: Paras@123 | D644: Medical Surgical Ward | E644: INCIDENT REPORTER | F644: Paras HMRI Patna | G644: Patna | H644: himanshu672614@gmail.com | I644: 6201724963 | J644: PT-PAT-06887 | K644: Anandita Namita Mundu | L644: Nursing | M644: Staff Nurse | N644: 45979 | O644: =INDEX(Med!J:J,MATCH(Paras!I644,Med!J:J,0)) -> #N/A | P644: =INDEX(Med!B:B,MATCH(Paras!J644,Med!B:B,0)) -> #N/A | Q644: =INDEX(Med!K:K,MATCH(Paras!H644,Med!K:K,0)) -> #N/A
A645: 644 | B645: Soumya Prakash | C645: Paras@123 | D645: Coordinator Pool | E645: INCIDENT REPORTER | F645: Paras HMRI Patna | G645: Patna | H645: drsoumya.prakash@parashospitals.com | I645: 9044978581 | J645: PT-PAT-06890 | K645: Manish Kumar | L645: Administration | M645: Assistant Manager | N645: 45981 | O645: =INDEX(Med!J:J,MATCH(Paras!I645,Med!J:J,0)) -> #N/A | P645: =INDEX(Med!B:B,MATCH(Paras!J645,Med!B:B,0)) -> #N/A | Q645: =INDEX(Med!K:K,MATCH(Paras!H645,Med!K:K,0)) -> #N/A
A646: 645 | B646: Shamma Anjum | C646: Paras@123 | D646: CCU | E646: INCIDENT REPORTER | F646: Paras HMRI Patna | G646: Patna | H646: shamaanjum949@gmail.com | I646: 7050842152 | J646: PT-PAT-06894 | K646: Archana Chandra | L646: Nursing | M646: Staff Nurse | N646: 45981 | O646: =INDEX(Med!J:J,MATCH(Paras!I646,Med!J:J,0)) -> #N/A | P646: =INDEX(Med!B:B,MATCH(Paras!J646,Med!B:B,0)) -> #N/A | Q646: =INDEX(Med!K:K,MATCH(Paras!H646,Med!K:K,0)) -> #N/A
A647: 646 | B647: Sonu Kumar | C647: Paras@123 | D647: IP Pharmacy | E647: INCIDENT REPORTER | F647: Paras HMRI Patna | G647: Patna | I647: 7541047066 | J647: PT-PAT-06895 | K647: Arbind Prasad | L647: Paramedics | M647: Sr. Pharmacist - Level 1 | N647: 45981 | O647: =INDEX(Med!J:J,MATCH(Paras!I647,Med!J:J,0)) -> #N/A | P647: =INDEX(Med!B:B,MATCH(Paras!J647,Med!B:B,0)) -> #N/A | Q647: =INDEX(Med!K:K,MATCH(Paras!H647,Med!K:K,0))
A648: 647 | B648: Deepankar Jangid | C648: Paras@123 | D648: Guest Relations | E648: INCIDENT REPORTER | F648: Paras HMRI Patna | G648: Patna | I648: 9783825459 | J648: PT-PAT-06897 | K648: Ramavtar Jangid | L648: Support | M648: Assistant Manager | N648: 45982 | O648: =INDEX(Med!J:J,MATCH(Paras!I648,Med!J:J,0)) -> #N/A | P648: =INDEX(Med!B:B,MATCH(Paras!J648,Med!B:B,0)) -> #N/A | Q648: =INDEX(Med!K:K,MATCH(Paras!H648,Med!K:K,0))
A649: 648 | B649: Monu Kumar | C649: Paras@123 | D649: Medical Surgical Ward | E649: INCIDENT REPORTER | F649: Paras HMRI Patna | G649: Patna | I649: 6203241483 | J649: PT-PAT-06898 | K649: Soni Paswan | L649: Nursing | M649: Sr. Staff Nurse | N649: 45982 | O649: =INDEX(Med!J:J,MATCH(Paras!I649,Med!J:J,0)) -> #N/A | P649: =INDEX(Med!B:B,MATCH(Paras!J649,Med!B:B,0)) -> #N/A | Q649: =INDEX(Med!K:K,MATCH(Paras!H649,Med!K:K,0))
A650: 649 | B650: Deepshikha Bhave | C650: Paras@123 | D650: Surgical Oncology-Head & Neck | E650: INCIDENT REPORTER | F650: Paras HMRI Patna | G650: Patna | I650: 9673783487 | J650: PT-PAT-06899 | K650: Manish Kumar | L650: Doctors | M650: Resident Medical Officer | N650: 45976 | O650: =INDEX(Med!J:J,MATCH(Paras!I650,Med!J:J,0)) -> #N/A | P650: =INDEX(Med!B:B,MATCH(Paras!J650,Med!B:B,0)) -> #N/A | Q650: =INDEX(Med!K:K,MATCH(Paras!H650,Med!K:K,0))
A651: 650 | B651: Punam Kumari | C651: Paras@123 | D651: Medical Surgical Ward | E651: INCIDENT REPORTER | F651: Paras HMRI Patna | G651: Patna | I651: 8521382944 | J651: PT-PAT-06900 | K651: Minakshi Pandey | L651: Nursing | M651: Staff Nurse | N651: 45982 | O651: =INDEX(Med!J:J,MATCH(Paras!I651,Med!J:J,0)) -> #N/A | P651: =INDEX(Med!B:B,MATCH(Paras!J651,Med!B:B,0)) -> #N/A | Q651: =INDEX(Med!K:K,MATCH(Paras!H651,Med!K:K,0))
A652: 651 | B652: Ravi Kumar | C652: Paras@123 | D652: General OT | E652: INCIDENT REPORTER | F652: Paras HMRI Patna | G652: Patna | I652: 8210073237 | J652: PT-PAT-06901 | K652: Neha Singh | L652: Paramedics | M652: Technician - Level 1 | N652: 45982 | O652: =INDEX(Med!J:J,MATCH(Paras!I652,Med!J:J,0)) -> #N/A | P652: =INDEX(Med!B:B,MATCH(Paras!J652,Med!B:B,0)) -> #N/A | Q652: =INDEX(Med!K:K,MATCH(Paras!H652,Med!K:K,0))
A653: 652 | B653: Bhola Mandal | C653: Paras@123 | D653: Medical Surgical Ward | E653: INCIDENT REPORTER | F653: Paras HMRI Patna | G653: Patna | I653: 9334525948 | J653: PT-PAT-06902 | K653: Punam Soren | L653: Nursing | M653: Staff Nurse | N653: 45982 | O653: =INDEX(Med!J:J,MATCH(Paras!I653,Med!J:J,0)) -> #N/A | P653: =INDEX(Med!B:B,MATCH(Paras!J653,Med!B:B,0)) -> #N/A | Q653: =INDEX(Med!K:K,MATCH(Paras!H653,Med!K:K,0))
A654: 653 | B654: Priyanka Kumari | C654: Paras@123 | D654: Medical Surgical Ward | E654: INCIDENT REPORTER | F654: Paras HMRI Patna | G654: Patna | I654: 7633897574 | J654: PT-PAT-06903 | K654: KM Priti Bharti | L654: Nursing | M654: Staff Nurse | N654: 45982 | O654: =INDEX(Med!J:J,MATCH(Paras!I654,Med!J:J,0)) -> #N/A | P654: =INDEX(Med!B:B,MATCH(Paras!J654,Med!B:B,0)) -> #N/A | Q654: =INDEX(Med!K:K,MATCH(Paras!H654,Med!K:K,0))
A655: 654 | B655: Sanket Kumar | C655: Paras@123 | D655: Internal Medicine | E655: INCIDENT REPORTER | F655: Paras HMRI Patna | G655: Patna | I655: 9804926232 | J655: PT-PAT-06904 | K655: Sudhakar Mishra | L655: Doctors | M655: Senior Medical Officer | N655: 45985 | O655: =INDEX(Med!J:J,MATCH(Paras!I655,Med!J:J,0)) -> #N/A | P655: =INDEX(Med!B:B,MATCH(Paras!J655,Med!B:B,0)) -> #N/A | Q655: =INDEX(Med!K:K,MATCH(Paras!H655,Med!K:K,0))
A656: 655 | B656: Shivani Kumari | C656: Paras@123 | D656: Billing | E656: INCIDENT REPORTER | F656: Paras HMRI Patna | G656: Patna | I656: 7204339055 | J656: PT-PAT-06905 | K656: Harendra Kumar Singh | L656: Administration | M656: Executive- Level 1 | N656: 45985 | O656: =INDEX(Med!J:J,MATCH(Paras!I656,Med!J:J,0)) -> #N/A | P656: =INDEX(Med!B:B,MATCH(Paras!J656,Med!B:B,0)) -> #N/A | Q656: =INDEX(Med!K:K,MATCH(Paras!H656,Med!K:K,0))
A657: 656 | B657: Md Gulzar Alam | C657: Paras@123 | D657: Medical Surgical Ward | E657: INCIDENT REPORTER | F657: Paras HMRI Patna | G657: Patna | I657: 9661321722 | J657: PT-PAT-06906 | K657: KM Priti Bharti | L657: Nursing | M657: Staff Nurse | N657: 45985 | O657: =INDEX(Med!J:J,MATCH(Paras!I657,Med!J:J,0)) -> #N/A | P657: =INDEX(Med!B:B,MATCH(Paras!J657,Med!B:B,0)) -> #N/A | Q657: =INDEX(Med!K:K,MATCH(Paras!H657,Med!K:K,0))
A658: 657 | B658: Ayush Kumar Singh | C658: Paras@123 | D658: Medical Surgical Ward | E658: INCIDENT REPORTER | F658: Paras HMRI Patna | G658: Patna | I658: 8009204768 | J658: PT-PAT-06907 | K658: Anandita Namita Mundu | L658: Nursing | M658: Staff Nurse | N658: 45985 | O658: =INDEX(Med!J:J,MATCH(Paras!I658,Med!J:J,0)) -> #N/A | P658: =INDEX(Med!B:B,MATCH(Paras!J658,Med!B:B,0)) -> #N/A | Q658: =INDEX(Med!K:K,MATCH(Paras!H658,Med!K:K,0))
... A711: 710 | B711: Mrityunjay Kumar | C711: Paras@123 | D711: Internal Medicine | E711: INCIDENT REPORTER | F711: Paras HMRI Patna | G711: Patna | I711: 7011706070 | J711: PT-PAT-06979 | K711: Anil Kumar | L711: Revenue Generating Doctors | M711: Director | N711: 46027 | O711: =INDEX(Med!J:J,MATCH(Paras!I711,Med!J:J,0)) -> #N/A | P711: =INDEX(Med!B:B,MATCH(Paras!J711,Med!B:B,0)) -> #N/A | Q711: =INDEX(Med!K:K,MATCH(Paras!H711,Med!K:K,0))
A712: 711 | B712: Manish Kumar | C712: Paras@123 | D712: Domestic Sales | E712: INCIDENT REPORTER | F712: Paras HMRI Patna | G712: Patna | H712: manish.kumar1@parashealth.com | I712: 9827103232 | J712: PT-PAT-06980 | K712: Rohit Kumar | L712: Administration | M712: Assistant Manager | N712: 46027 | O712: =INDEX(Med!J:J,MATCH(Paras!I712,Med!J:J,0)) -> #N/A | P712: =INDEX(Med!B:B,MATCH(Paras!J712,Med!B:B,0)) -> #N/A | Q712: =INDEX(Med!K:K,MATCH(Paras!H712,Med!K:K,0)) -> #N/A
A713: 712 | B713: Preeti Kumari | C713: Paras@123 | D713: Dispatch | E713: INCIDENT REPORTER | F713: Paras HMRI Patna | G713: Patna | I713: 7301955408 | J713: PT-PAT-06981 | K713: Shailesh Mauar | L713: Administration | M713: Sr. Executive- Level 1 | N713: 46027 | O713: =INDEX(Med!J:J,MATCH(Paras!I713,Med!J:J,0)) -> #N/A | P713: =INDEX(Med!B:B,MATCH(Paras!J713,Med!B:B,0)) -> #N/A | Q713: =INDEX(Med!K:K,MATCH(Paras!H713,Med!K:K,0))
A714: 713 | B714: Rajveer Saran | C714: Paras@123 | D714: OP Billing | E714: INCIDENT REPORTER | F714: Paras HMRI Patna | G714: Patna | I714: 9576963869 | J714: PT-PAT-06982 | K714: Ramavtar Jangid | L714: Support | M714: Executive- Level 1 | N714: 46027 | O714: =INDEX(Med!J:J,MATCH(Paras!I714,Med!J:J,0)) -> #N/A | P714: =INDEX(Med!B:B,MATCH(Paras!J714,Med!B:B,0)) -> #N/A | Q714: =INDEX(Med!K:K,MATCH(Paras!H714,Med!K:K,0))
A715: 714 | B715: Anima Balbandi | C715: Paras@123 | D715: Medical Surgical Ward | E715: INCIDENT REPORTER | F715: Paras HMRI Patna | G715: Patna | I715: 8252383073 | J715: PT-PAT-06983 | K715: Jibi Varghese | L715: Nursing | M715: Ward Incharge | N715: 46027 | O715: =INDEX(Med!J:J,MATCH(Paras!I715,Med!J:J,0)) -> #N/A | P715: =INDEX(Med!B:B,MATCH(Paras!J715,Med!B:B,0)) -> #N/A | Q715: =INDEX(Med!K:K,MATCH(Paras!H715,Med!K:K,0))
A716: 715 | B716: Nisha Kumari | C716: Paras@123 | D716: MICU | E716: INCIDENT REPORTER | F716: Paras HMRI Patna | G716: Patna | I716: 9135101903 | J716: PT-PAT-06984 | K716: Reena Kumari | L716: Nursing | M716: Staff Nurse | N716: 46027 | O716: =INDEX(Med!J:J,MATCH(Paras!I716,Med!J:J,0)) -> #N/A | P716: =INDEX(Med!B:B,MATCH(Paras!J716,Med!B:B,0)) -> #N/A | Q716: =INDEX(Med!K:K,MATCH(Paras!H716,Med!K:K,0))
A717: 716 | B717: Komal Kumari | C717: Paras@123 | D717: Medical Surgical Ward | E717: INCIDENT REPORTER | F717: Paras HMRI Patna | G717: Patna | I717: 7479885762 | J717: PT-PAT-06986 | K717: KM Priti Bharti | L717: Nursing | M717: Staff Nurse | N717: 46027 | O717: =INDEX(Med!J:J,MATCH(Paras!I717,Med!J:J,0)) -> #N/A | P717: =INDEX(Med!B:B,MATCH(Paras!J717,Med!B:B,0)) -> #N/A | Q717: =INDEX(Med!K:K,MATCH(Paras!H717,Med!K:K,0))
A718: 717 | B718: Rohit Kumar | C718: Paras@123 | D718: Sales & Marketing | E718: INCIDENT REPORTER | F718: Paras HMRI Patna | G718: Patna | I718: 7759855272 | J718: PT-PAT-06987 | K718: Anil Kumar | L718: Administration | M718: Senior General Manager | N718: 46028 | O718: =INDEX(Med!J:J,MATCH(Paras!I718,Med!J:J,0)) -> #N/A | P718: =INDEX(Med!B:B,MATCH(Paras!J718,Med!B:B,0)) -> #N/A | Q718: =INDEX(Med!K:K,MATCH(Paras!H718,Med!K:K,0))
A719: 718 | B719: Trishna Chatterjee | C719: Paras@123 | D719: Coordinator Pool | E719: INCIDENT REPORTER | F719: Paras HMRI Patna | G719: Patna | I719: 8918763221 | J719: PT-PAT-06988 | K719: Md Shariful Haque | L719: Administration | M719: Executive- Level 1 | N719: 46028 | O719: =INDEX(Med!J:J,MATCH(Paras!I719,Med!J:J,0)) -> #N/A | P719: =INDEX(Med!B:B,MATCH(Paras!J719,Med!B:B,0)) -> #N/A | Q719: =INDEX(Med!K:K,MATCH(Paras!H719,Med!K:K,0))
A720: 719 | B720: Syed Zulfequar Ashraf | C720: Paras@123 | D720: Medical Surgical Ward | E720: INCIDENT REPORTER | F720: Paras HMRI Patna | G720: Patna | I720: 7050202180 | J720: PT-PAT-06989 | K720: Soni Paswan | L720: Nursing | M720: Staff Nurse | N720: 46028 | O720: =INDEX(Med!J:J,MATCH(Paras!I720,Med!J:J,0)) -> #N/A | P720: =INDEX(Med!B:B,MATCH(Paras!J720,Med!B:B,0)) -> #N/A | Q720: =INDEX(Med!K:K,MATCH(Paras!H720,Med!K:K,0))
A721: 720 | B721: Sonam Kumari | C721: Paras@123 | D721: Non Invasive Cardiology | E721: INCIDENT REPORTER | F721: Paras HMRI Patna | G721: Patna | I721: 8210500740 | J721: PT-PAT-06990 | K721: Manish Kumar | L721: Paramedics | M721: Technician - Level 1 | N721: 46028 | O721: =INDEX(Med!J:J,MATCH(Paras!I721,Med!J:J,0)) -> #N/A | P721: =INDEX(Med!B:B,MATCH(Paras!J721,Med!B:B,0)) -> #N/A | Q721: =INDEX(Med!K:K,MATCH(Paras!H721,Med!K:K,0))
A722: 721 | B722: Neha Singh | C722: Paras@123 | D722: Operation Theater | E722: INCIDENT REPORTER | F722: Paras HMRI Patna | G722: Patna | I722: 9162854831 | J722: PT-PAT-06991 | K722: Manish Kumar | L722: Paramedics | M722: Manager | N722: 46030 | O722: =INDEX(Med!J:J,MATCH(Paras!I722,Med!J:J,0)) -> #N/A | P722: =INDEX(Med!B:B,MATCH(Paras!J722,Med!B:B,0)) -> #N/A | Q722: =INDEX(Med!K:K,MATCH(Paras!H722,Med!K:K,0))
A723: 722 | B723: Taufiq Ehsan | C723: Paras@123 | D723: CSSD | E723: INCIDENT REPORTER | F723: Paras HMRI Patna | G723: Patna | I723: 8235891264 | J723: PT-PAT-06992 | K723: Atishay Ranjan | L723: Paramedics | M723: Technician - Level 1 | N723: 46034 | O723: =INDEX(Med!J:J,MATCH(Paras!I723,Med!J:J,0)) -> #N/A | P723: =INDEX(Med!B:B,MATCH(Paras!J723,Med!B:B,0)) -> #N/A | Q723: =INDEX(Med!K:K,MATCH(Paras!H723,Med!K:K,0))
A724: 723 | B724: Jyoti | C724: Paras@123 | D724: Guest Relations | E724: INCIDENT REPORTER | F724: Paras HMRI Patna | G724: Patna | I724: 8882593259 | J724: PT-PAT-06993 | K724: Ramavtar Jangid | L724: Support | M724: Executive- Level 1 | N724: 46034 | O724: =INDEX(Med!J:J,MATCH(Paras!I724,Med!J:J,0)) -> #N/A | P724: =INDEX(Med!B:B,MATCH(Paras!J724,Med!B:B,0)) -> #N/A | Q724: =INDEX(Med!K:K,MATCH(Paras!H724,Med!K:K,0))
...

Sheet existing
A1: Sr. NO | B1: userName | C1: password | D1: departments | E1: roles | F1: Exising_role | G1: units | H1: locations | I1: Mail ID | J1: Personal Phone | K1: employeeId | L1: Reporting To | M1: Category Code | N1: Designation Name | O1: Date Of Joining
A2: 3 | B2: Priyasmita Chattapadhyay | C2: Paras@123 | D2: Guest Relations | E2: INCIDENT REPORTER | F2: Incident Reporter|Feedback Duplicator|QI Viewer|PRE 0 - Staff Responsiveness and Behaviour|PRE 1 - Staff Responsiveness and Behaviour|PRE 1|Feedback Dashboard Viewer|PRE 1 - Paras Updates|Audit User - Patient Arrival Audit|Feedback Collector|PRE 0|Feedback Review Reassigner | G2: Paras HMRI Patna | H2: Patna | I2: priyasmitactjee888@gmail.com | J2: 8240873293 | K2: PT-PA05901 | L2: Ramavtar Jangid | M2: Support | N2: Sr. Executive- Level 1 | O2: 45288
A3: 11 | B3: Jibi Varghese | C3: Paras@123 | D3: Nursing Administration | E3: INCIDENT REPORTER | F3: Incident Reporter|PRE 1 - Care from Nurses|QI Viewer|Incident Analyst|Audit User|Audit Incharge|PRE 1 - Nursing Services | G3: Paras HMRI Patna | H3: Patna | I3: Jibijosejace@Gmail.Com | J3: 7654346060 | K3: PT-PAT-00152 | L3: Subhra Ghatak | M3: Nursing | N3: Manager | O3: 41457
A4: 15 | B4: Srinarayan | C4: Paras@123 | D4: General Anaesthesia | E4: INCIDENT REPORTER | F4: Incident Reporter|QI Viewer|Incident Analyst|Audit Incharge - Prophylactic Antibiotic Compliance Audit|Audit Incharge - CPR Audit | G4: Paras HMRI Patna | H4: Patna | I4: srinarayan45@gmail.com | J4: 9835293334 | K4: PT-PAT-00231 | L4: Anil Kumar | M4: Doctors | N4: Principal Consultant | O4: 41465
A5: 17 | B5: Abhishek Kumar | C5: Paras@123 | D5: Coordinator Pool | E5: INCIDENT REPORTER | F5: Incident Reporter|QI Viewer|Incident Analyst|Audit User|Audit Incharge|PRE 2 - Admission Process|PRE 2 - Admission Experience|PRE 2 - Call Centre|PRE 2 - OPD / ER Billing | G5: Paras HMRI Patna | H5: Patna | I5: kumar.abhishek@parashospitals.com | J5: 8252672281 | K5: PT-PAT-00244 | L5: Ramavtar Jangid | M5: Administration | N5: Sr. Manager | O5: 41466
A6: 22 | B6: Meena Goswami | C6: Paras@123 | D6: Ortho OT | E6: INCIDENT REPORTER | F6: Incident Reporter|QI Viewer | G6: Paras HMRI Patna | H6: Patna | I6: meena123@gmail.com | J6: 9631995901 | K6: PT-PAT-00278 | L6: Neha Singh | M6: Nursing | N6: Trainee Staff Nurse | O6: 41477
A7: 47 | B7: Rufina Kispotta | C7: Paras@123 | D7: CCU | E7: INCIDENT REPORTER | F7: Incident Reporter|QI Viewer | G7: Paras HMRI Patna | H7: Patna | I7: Rufinakispotta074@Gmail.Com | J7: 7781866326 | K7: PT-PAT-00788 | L7: Archana Chandra | M7: Nursing | N7: Sr. Staff Nurse | O7: 41663
A8: 52 | B8: Syed Md. Shamsheer Ahmad | C8: Paras@123 | D8: Blood Bank | E8: INCIDENT REPORTER | F8: Audit User|Audit Incharge|Audit Admin|Feedback Leadership Dashboard Viewer|Feedback Dashboard Viewer|Incident Level 3 approver|Incident RCA Approver|Incident RCA Reviewer|Incident Incharge|Incident Analyst|Incident Admin|Incident Advisor|Incident Officer|Incident Dashboard Viewer|Feedback Collector | G8: Paras HMRI Patna | H8: Patna | I8: Shamsheer1988@gmail.com | J8: 9905724241 | K8: PT-PAT-01163 | L8: Manish Kumar | M8: Paramedics | N8: Deputy Manager | O8: 41857
A9: 58 | B9: Suchita Kujur | C9: Paras@123 | D9: OPD | E9: INCIDENT REPORTER | F9: Incident Reporter|QI Viewer | G9: Paras HMRI Patna | H9: Patna | I9: suchitakujur41@gmail.com | J9: 8102201940 | K9: PT-PAT-01347 | L9: Durgabati Kumari | M9: Nursing | N9: Trainee Staff Nurse | O9: 41976
A10: 62 | B10: Neha Mehta | C10: Paras@123 | D10: Respiratory ICU | E10: INCIDENT REPORTER | F10: Incident Reporter|QI Viewer | G10: Paras HMRI Patna | H10: Patna | I10: nehamehta3131@gmail.com | J10: 9835834915 | K10: PT-PAT-01399 | L10: Jibi Varghese | M10: Nursing | N10: Ward Incharge | O10: 41989
A11: 65 | B11: Sunita Kisku | C11: Paras@123 | D11: OPD | E11: INCIDENT REPORTER | F11: Incident Reporter|QI Viewer | G11: Paras HMRI Patna | H11: Patna | I11: SUNITAKISKU311289@GMAIL.COM | J11: 9546618442 | K11: PT-PAT-01467 | L11: Durgabati Kumari | M11: Nursing | N11: Trainee Staff Nurse | O11: 42072
A12: 73 | B12: Harendra Kumar Divakar | C12: Paras@123 | D12: Medical Record Room | E12: INCIDENT REPORTER | F12: Incident Reporter|QI Viewer|Incident Analyst|Hospital Statistics Admin - General Statistics|Hospital Statistics User - General Statistics|Hospital Statistics User - Quality Statistics|Audit User - Passive file audit | G12: Paras HMRI Patna | H12: Patna | I12: Harendra_Hm003@Yahoo.Co.In | J12: 9631412647 | K12: PT-PAT-01824 | L12: Manish Kumar | M12: Paramedics | N12: Deputy Manager | O12: 42296
A13: 74 | B13: Sandhya Kumari | C13: Paras@123 | D13: OPD | E13: INCIDENT REPORTER | F13: Incident Reporter|QI Viewer | G13: Paras HMRI Patna | H13: Patna | I13: sandhya1712@gmail.com | J13: 7654636608 | K13: PT-PAT-01933 | L13: Durgabati Kumari | M13: Nursing | N13: Trainee Staff Nurse | O13: 42357
... A46: 601 | B46: Vishal Kumar | C46: Paras@123 | D46: Biomedical Engineering | E46: INCIDENT REPORTER | F46: Incident Reporter|QI Viewer | G46: Paras HMRI Patna | H46: Patna | I46: BIOMEDICAL.PATNA@PARASHOSPITALS.COM | J46: 6207474258 | K46: PT-PAT-06819 | L46: Dharmendra Kumar | M46: Support | N46: Engineer- Level 1 | O46: 45931
A47: 667 | B47: Mohd Shahabuddin | C47: Paras@123 | D47: Engineering & Maintenance | E47: INCIDENT REPORTER | F47: PRE 1 - Maintenance|QI Viewer|PRE 2 - Maintenance|PRE 3 - Maintenance|Feedback Leadership Dashboard Viewer|Feedback Dashboard Viewer|PRE 1|PRE 2|PRE 3|PRE 0|PRE 0 - Maintenance | G47: Paras HMRI Patna | H47: Patna | J47: 9911077433 | K47: PT-PAT-06922 | L47: Ramavtar Jangid | M47: Support | N47: Deputy Manager | O47: 45992
A48: 689 | B48: Amit Kumar Aman | C48: Paras@123 | D48: Security | E48: INCIDENT REPORTER | F48: QI Viewer|PRE 0 - Security Services|PRE 1 - Security Services|PRE 0 - Security|PRE 1 - Security|Hospital Statistics User - security Stats | G48: Paras HMRI Patna | H48: Patna | J48: 7303402503 | K48: PT-PAT-06954 | L48: Jasmer Singh | M48: Support | N48: Manager | O48: 46007
A49: 703 | B49: Subhra Ghatak | C49: Paras@123 | D49: Nursing Administration | E49: INCIDENT REPORTER | F49: Incident Reporter|PRE 1 - Care from Nurses|PRE 2 - Care from Nurses|QI Viewer|Incident Analyst|Audit User|Audit Incharge|PRE 1 - Nursing Services|PRE 2 - Nursing Services | G49: Paras HMRI Patna | H49: Patna | J49: 8240613095 | K49: PT-PAT-06971 | L49: Manish Kumar | M49: Nursing | N49: Associate General Manager | O49: 46015
A50: 835 | B50: Prashant Sen | C50: Paras@123 | D50: Hospital Operations | E50: INCIDENT REPORTER | F50: Incident Reporter|QI Viewer|Incident Analyst|Audit Incharge|Feedback Dashboard Viewer|PRE 2|Audit User - Patient Arrival Audit|Feedback Collector|Feedback Review Reassigner | G50: Paras HMRI Patna | H50: Patna | I50: p8789singh@gmail.com | J50: 7061163204 | K50: PT-PAT-07119 | L50: Ramavtar Jangid | M50: Administration | N50: Assistant Manager | O50: 46113
A51: 852 | B51: Hari Shanker | C51: Paras@123 | D51: Cardiothoracic and Vascular Surgery | E51: INCIDENT REPORTER | F51: Incident Reporter|QI Viewer | G51: Paras HMRI Patna | H51: Patna | I51: hari.pandey0@gmail.com | J51: 7000948243 | K51: PT-PAT-07137 | L51: Manish Kumar | M51: Paramedics | N51: Physician Assistant - Level 1 | O51: 46118
A52: 328 | B52: Neeraj Kumar | C52: Paras@123 | D52: Accounts | E52: INCIDENT REPORTER | F52: Incident Reporter|QI Viewer|Incident Analyst|Audit User|Audit Incharge | G52: Paras HMRI Patna | H52: Patna | I52: neeraj.kumar@parashospitals.com | J52: 9810870948 | K52: PT-PAT-06079 | L52: Anil Kumar | M52: Administration | N52: Deputy General Manager | O52: 45500
A53: 19 | B53: Baby Nisha | C53: Paras@123 | D53: Ortho OT | E53: INCIDENT REPORTER | F53: Incident Reporter|QI Viewer | G53: Paras HMRI Patna | H53: Patna | I53: Babyxnisha@Gmail.Com | J53: 9279735483 | K53: PT-PAT-00272 | L53: Neha Singh | M53: Nursing | N53: Trainee Staff Nurse | O53: 41477
A54: 23 | B54: Sabita Devi | C54: Paras@123 | D54: Ortho OT | E54: INCIDENT REPORTER | F54: Incident Reporter|QI Viewer | G54: Paras HMRI Patna | H54: Patna | I54: sabitabharti2004@gmail.com | J54: 9304465035 | K54: PT-PAT-00279 | L54: Neha Singh | M54: Nursing | N54: Trainee Staff Nurse | O54: 41477
A55: 57 | B55: Seema Bara | C55: Paras@123 | D55: MICU | E55: INCIDENT REPORTER | F55: Incident Reporter|QI Viewer | G55: Paras HMRI Patna | H55: Patna | I55: seemabara1340@gmail.com | J55: 7541988044 | K55: PT-PAT-01340 | L55: Jibi Varghese | M55: Nursing | N55: Nurse Incharge | O55: 41974
A56: 59 | B56: Suby Paul | C56: Paras@123 | D56: Nursing Administration | E56: INCIDENT REPORTER | F56: Incident Reporter|QI Viewer | G56: Paras HMRI Patna | H56: Patna | I56: Suby010@Gmail.Com | J56: 9162927034 | K56: PT-PAT-01362 | L56: Jibi Varghese | M56: Nursing | N56: Supervisor | O56: 41986
A57: 64 | B57: Srimati Gope | C57: Paras@123 | D57: Nursing Administration | E57: INCIDENT REPORTER | F57: Incident Reporter|QI Viewer|Audit User | G57: Paras HMRI Patna | H57: Patna | I57: srimati@gmail.com | J57: 8809868887 | K57: PT-PAT-01463 | L57: Jibi Varghese | M57: Nursing | N57: Supervisor | O57: 42066
A58: 100 | B58: Archana Chandra | C58: Paras@123 | D58: CCU | E58: INCIDENT REPORTER | F58: Incident Reporter|QI Viewer | G58: Paras HMRI Patna | H58: Patna | I58: Archanachandra95@Gmail.Com | J58: 9896375231 | K58: PT-PAT-02803 | L58: Jibi Varghese | M58: Nursing | N58: Ward Incharge | O58: 43054
A59: 139 | B59: Bijendra Yadav | C59: Paras@123 | D59: Pre & Post Operations | E59: INCIDENT REPORTER | F59: Incident Reporter|QI Viewer | G59: Paras HMRI Patna | H59: Patna | I59: bijendra10196@gmail.com | J59: 8102578832 | K59: PT-PAT-04166 | L59: Manisha Kumari | M59: Nursing | N59: Staff Nurse | O59: 44120
A60: 141 | B60: Onkar Mani Tirpathi | C60: Paras@123 | D60: Emergency | E60: INCIDENT REPORTER | F60: Incident Reporter|QI Viewer | G60: Paras HMRI Patna | H60: Patna | I60: onkarmanitripathi25756@gmail.com | J60: 8858659783 | K60: PT-PAT-04194 | L60: Jibi Varghese | M60: Nursing | N60: Sr. Staff Nurse | O60: 44133
A61: 550 | B61: Mohit Verma | C61: Paras@123 | D61: Nursing Administration | E61: INCIDENT REPORTER | F61: PRE 1 - Care from Nurses|Incident Reporter|QI Viewer|Incident Analyst|Audit User|PRE 1 - Nursing Services|Audit Incharge | G61: Paras HMRI Patna | H61: Patna | I61: mohitv9550@gmail.com | J61: 9855751498 | K61: PT-PAT-06744 | L61: Subhra Ghatak | M61: Nursing | N61: Assistant Manager | O61: 45887

Sheet New_User
A1: Sr. NO | B1: userName | C1: password | D1: departments | E1: roles | F1: units | G1: locations | H1: Mail ID | I1: Personal Phone | J1: employeeId | K1: Reporting To | L1: Category Code | M1: Designation Name | N1: Date Of Joining
A2: 1 | B2: shivangi | C2: Paras@123 | D2: Respiratory ICU | E2: Incident Reporter | F2: Paras HMRI Patna | G2: Patna | H2: ranishivangi9199@gmail.com | I2: 9199023328 | J2: PT-PA05897 | K2: Neha Mehta | L2: Nursing | M2: Staff Nurse | N2: 45281
A3: 2 | B3: divyayadav | C3: Paras@123 | D3: EMERGENCY | E3: Incident Reporter | F3: Paras HMRI Patna | G3: Patna | H3: dilipyadav199091@gmail.com | I3: 7905497275 | J3: PT-PA05899 | K3: Onkar Mani Tirpathi | L3: Nursing | M3: Sr. Staff Nurse | N3: 45282
A4: 4 | B4: nishantsingh | C4: Paras@123 | D4: NEUROLOGY | E4: Incident Reporter | F4: Paras HMRI Patna | G4: Patna | H4: nishantsingh19@gmail.com | I4: 7903950921 | J4: PT-PA05902 | K4: Manish Kumar | L4: Doctors | M4: DNB Primary - 1 | N4: 45288
A5: 5 | B5: sujayranjan | C5: Paras@123 | D5: NEPHROLOGY | E5: Incident Reporter | F5: Paras HMRI Patna | G5: Patna | H5: sujaynmch@gmail.com | I5: 9430559937 | J5: PT-PA05904 | K5: Manish Kumar | L5: Doctors | M5: DNB Primary - 1 | N5: 45293
A6: 6 | B6: premchandrakumar | C6: Paras@123 | D6: DISPATCH CENTER | E6: Incident Reporter | F6: Paras HMRI Patna | G6: Patna | H6: PREMPARASHMRI@GMAIL.COM | I6: 6202743641 | J6: PT-PAT-00035 | K6: Shailesh Mauar | L6: Administration | M6: Office Assistant- Level 1 | N6: 41426
A7: 7 | B7: abhishek | C7: Paras@123 | D7: NEUROLOGY | E7: Incident Reporter | F7: Paras HMRI Patna | G7: Patna | H7: drabhishek.kumar@parashospitals.com | I7: 9431432955 | J7: PT-PAT-00109 | K7: Anil Kumar | L7: Doctors | M7: Senior Consultant | N7: 41456
A8: 8 | B8: bineetasinha | C8: Paras@123 | D8: Pathology | E8: Incident Reporter | F8: Paras HMRI Patna | G8: Patna | H8: drbineeta.sinha@parashospitals.com | I8: 7858888175 | J8: PT-PAT-00110 | K8: Anil Kumar | L8: Doctors | M8: Principal Consultant | N8: 41456
A9: 9 | B9: masihullah | C9: Paras@123 | D9: MAMBS | E9: Incident Reporter | F9: Paras HMRI Patna | G9: Patna | H9: drmashiullah@parashospitals.com | I9: 9835848120 | J9: PT-PAT-00113 | K9: Manish Kumar | L9: Doctors | M9: Associate Director | N9: 41456
A10: 10 | B10: gautamrambabuprasad | C10: Paras@123 | D10: ORTHOPEDICS | E10: Incident Reporter | F10: Paras HMRI Patna | G10: Patna | H10: careforspine@yahoo.com | I10: 8877667722 | J10: PT-PAT-00122 | K10: Anil Kumar | L10: Revenue Generating Doctors | M10: Associate Director | N10: 41487
A11: 12 | B11: vinodkthakur | C11: Paras@123 | D11: ORTHOPEDICS | E11: Incident Reporter | F11: Paras HMRI Patna | G11: Patna | H11: drvinodkrthakur@gmail.com | I11: 9431041154 | J11: PT-PAT-00197 | K11: Anil Kumar | L11: Revenue Generating Doctors | M11: Associate Director | N11: 41487
A12: 13 | B12: rahulgarg | C12: Paras@123 | D12: NEUROLOGY | E12: Incident Reporter | F12: Paras HMRI Patna | G12: Patna | H12: rahul.garg5551@gmail.com | I12: 9334385551 | J12: PT-PAT-00219 | K12: Manish Kumar | L12: Paramedics | M12: Sr. Technician - Level 1 | N12: 41465
A13: 14 | B13: shekarkeshri | C13: Paras@123 | D13: ONCOLOGY | E13: Incident Reporter | F13: Paras HMRI Patna | G13: Patna | H13: drshekhar.keshri@parashospitals.com | I13: 9973043603 | J13: PT-PAT-00230 | K13: Anil Kumar | L13: Doctors | M13: Director | N13: 41465
... A32: 38 | B32: ahmadabdulhai | C32: Paras@123 | D32: MAMBS | E32: Incident Reporter | F32: Paras HMRI Patna | G32: Patna | H32: draahai@parashospitals.com | I32: 9304972834 | J32: PT-PAT-00465 | K32: Anil Kumar | L32: Doctors | M32: Director | N32: 41487
A33: 39 | B33: johnmukhopadhyay | C33: Paras@123 | D33: ORTHOPEDICS | E33: Incident Reporter | F33: Paras HMRI Patna | G33: Patna | H33: drjhon@parashospitals.com | J33: PT-PAT-00466 | K33: Anil Kumar | L33: Revenue Generating Doctors | M33: Director | N33: 41487
A34: 40 | B34: rajivranjan | C34: Paras@123 | D34: PEDIATRICS | E34: Incident Reporter | F34: Paras HMRI Patna | G34: Patna | H34: drrajivranjan@yahoo.com | I34: 9801835440 | J34: PT-PAT-00483 | K34: Anil Kumar | L34: Doctors | M34: Senior Consultant | N34: 41533
A35: 41 | B35: mdmoshirulislamkhan | C35: Paras@123 | D35: OT | E35: Incident Reporter | F35: Paras HMRI Patna | G35: Patna | H35: mikhan286@gmail.com | I35: 9308897408 | J35: PT-PAT-00564 | K35: Neha Singh | L35: Paramedics | M35: Sr. Technician - Level 1 | N35: 41557
A36: 42 | B36: anjanimehra | C36: Paras@123 | D36: NEUROLOGY | E36: Incident Reporter | F36: Paras HMRI Patna | G36: Patna | H36: dranjanimehra091@gmail.com | I36: 9507008008 | J36: PT-PAT-00698 | K36: Manish Kumar | L36: Doctors | M36: Attending Consultant | N36: 41628
A37: 43 | B37: ravibhaskar | C37: Paras@123 | D37: Pharmacy | E37: Incident Reporter | F37: Paras HMRI Patna | G37: Patna | H37: acmailmetest@gmail.com | I37: 7004320579 | J37: PT-PAT-00714 | K37: Arbind Prasad | L37: Paramedics | M37: Sr. Pharmacist - Level 1 | N37: 41575
A38: 44 | B38: avinashkumarsingh | C38: Paras@123 | D38: HEMATOLOGY | E38: Incident Reporter | F38: Paras HMRI Patna | G38: Patna | H38: avanish.kumar@parashospitals.com | I38: 9960945860 | J38: PT-PAT-00727 | K38: Anil Kumar | L38: Revenue Generating Doctors | M38: Director | N38: 41641
A39: 45 | B39: mazharulhaque | C39: Paras@123 | D39: Biochemistry | E39: Incident Reporter | F39: Paras HMRI Patna | G39: Patna | H39: mazharulhaque71@gmail.com | I39: 7903281806 | J39: PT-PAT-00729 | K39: Ravi Ranjan Kumar | L39: Paramedics | M39: Sr. Technician - Level 2 | N39: 41641
A40: 46 | B40: sushilkumar | C40: Paras@123 | D40: Endoscopy Suite | E40: Incident Reporter | F40: Paras HMRI Patna | G40: Patna | H40: kumarsunil1111@gmail.com | I40: 9955569687 | J40: PT-PAT-00768 | K40: Manish Kumar | L40: Paramedics | M40: Technician - Level 1 | N40: 41655
A41: 48 | B41: mdkhurshidalam | C41: Paras@123 | D41: OT | E41: Incident Reporter | F41: Paras HMRI Patna | G41: Patna | H41: khurshid.alam2010@yahoo.com | I41: 9155581676 | J41: PT-PAT-00937 | K41: Neha Singh | L41: Paramedics | M41: Senior Supervisor | N41: 41739
A42: 49 | B42: satishsrivastava | C42: Paras@123 | D42: GENERAL & ADMINISTRTIVE SERVICES | E42: Incident Reporter | F42: Paras HMRI Patna | G42: Patna | H42: satish.bstdc@gmail.com | I42: 8002150150 | J42: PT-PAT-00950 | K42: Ramavtar Jangid | L42: Administration | M42: Deputy Manager | N42: 41744
A43: 50 | B43: chandankumarjha | C43: Paras@123 | D43: BLOOD BANK | E43: Incident Reporter | F43: Paras HMRI Patna | G43: Patna | H43: CANDANJHA1985@GMAIL.COM | I43: 6201482174 | J43: PT-PAT-01042 | K43: Syed Md. Shamsheer Ahmad | L43: Paramedics | M43: Sr. Technician - Level 1 | N43: 41792
A44: 51 | B44: amreshkumar | C44: Paras@123 | D44: NEUROLOGY | E44: Incident Reporter | F44: Paras HMRI Patna | G44: Patna | H44: amreshkumar5186@gmail.com | I44: 7766021111 | J44: PT-PAT-01134 | K44: Manish Kumar | L44: Doctors | M44: Senior Medical Officer | N44: 41848
A45: 53 | B45: pankajudas | C45: Paras@123 | D45: SECURITY | E45: Incident Reporter | F45: Paras HMRI Patna | G45: Patna | H45: Udhaspankaj6@gmail.com | I45: 9570559944 | J45: PT-PAT-01170 | K45: Jasmer Singh | L45: Support | M45: Assistant Manager | N45: 41863
... A275: 317 | B275: vivekkumar | C275: Paras@123 | D275: BLOOD BANK | E275: Incident Reporter | F275: Paras HMRI Patna | G275: Patna | H275: VIVEKLUMAR012796@GMAIL.COM | I275: 8227957463 | J275: PT-PAT-06055 | K275: Syed Md. Shamsheer Ahmad | L275: Paramedics | M275: Technician - Level 1 | N275: 45425
A276: 318 | B276: anilkumar | C276: Paras@123 | D276: HOSPITAL OPERATIONS | E276: Incident Reporter | F276: Paras HMRI Patna | G276: Patna | H276: kumar.anil@parashospitals.com | I276: 9950067666 | J276: PT-PAT-06060 | L276: Administration | M276: Zonal Director | N276: 45434
A277: 319 | B277: neerajsinha | C277: Paras@123 | D277: Endocrinology | E277: Incident Reporter | F277: Paras HMRI Patna | G277: Patna | H277: dr.neerajsinha@gmail.com | I277: 9748718138 | J277: PT-PAT-06063 | K277: Anil Kumar | L277: Revenue Generating Doctors | M277: Senior Consultant | N277: 45444
A278: 320 | B278: ramavtarjangid | C278: Paras@123 | D278: FRONT OFFICE | E278: Incident Reporter | F278: Paras HMRI Patna | G278: Patna | H278: ramavtar.jangid@parashospitals.com | I278: 9587112029 | J278: PT-PAT-06064 | K278: Anil Kumar | L278: Support | M278: General Manager | N278: 45476
A279: 321 | B279: payalpandey | C279: Paras@123 | D279: SALES & MARKETING | E279: Incident Reporter | F279: Paras HMRI Patna | G279: Patna | H279: payal.pandey@parashospitals.com | I279: 7091819078 | J279: PT-PAT-06065 | K279: Rohit Kumar | L279: Administration | M279: Assistant Manager | N279: 45476
A280: 322 | B280: shivamkumar | C280: Paras@123 | D280: SALES & MARKETING | E280: Incident Reporter | F280: Paras HMRI Patna | G280: Patna | H280: shivamsingh22295@gmail.com | I280: 7908835002 | J280: PT-PAT-06066 | K280: Rohit Kumar | L280: Administration | M280: Manager | N280: 45476
A281: 323 | B281: ranukumar | C281: Paras@123 | D281: SALES & MARKETING | E281: Incident Reporter | F281: Paras HMRI Patna | G281: Patna | H281: ranubhardwaj2846@gmail.com | I281: 9905769823 | J281: PT-PAT-06067 | K281: Rohit Kumar | L281: Administration | M281: Assistant Manager | N281: 45477
A282: 324 | B282: vishalanand | C282: Paras@123 | D282: Pharmacy | E282: Incident Reporter | F282: Paras HMRI Patna | G282: Patna | H282: vishalanand2222@gmail.com | I282: 6205754459 | J282: PT-PAT-06068 | K282: Arbind Prasad | L282: Paramedics | M282: Sr. Pharmacist - Level 1 | N282: 45478
A283: 325 | B283: ratneshraj | C283: Paras@123 | D283: Pharmacy | E283: Incident Reporter | F283: Paras HMRI Patna | G283: Patna | H283: rajratnesh89@gmail.com | I283: 9973044800 | J283: PT-PAT-06069 | K283: Arbind Prasad | L283: Paramedics | M283: Pharmacist - Level 1 | N283: 45478
A284: 326 | B284: pallabpati | C284: Paras@123 | D284: ONCOLOGY | E284: Incident Reporter | F284: Paras HMRI Patna | G284: Patna | H284: pallabpati8@gmail.com | I284: 8250667262 | J284: PT-PAT-06074 | K284: Jesu Jackin Lawrence | L284: Paramedics | M284: Sr. Technician - Level 1 | N284: 45495
A285: 327 | B285: harendrakumarsingh | C285: Paras@123 | D285: BILLING | E285: Incident Reporter | F285: Paras HMRI Patna | G285: Patna | H285: harendrakumar@singh@parashospitals.com | I285: 9811404042 | J285: PT-PAT-06078 | K285: Ramavtar Jangid | L285: Administration | M285: Sr. Manager | N285: 45499
A286: 329 | B286: firojalam | C286: Paras@123 | D286: MEDICAL SERVICES | E286: Incident Reporter | F286: Paras HMRI Patna | G286: Patna | H286: Falam2688@Gmail.Com | I286: 7033067294 | J286: PT-PAT-06086 | K286: Minakshi Pandey | L286: Nursing | M286: Staff Nurse | N286: 45502
A287: 330 | B287: minakshipandey | C287: Paras@123 | D287: MEDICAL SERVICES | E287: Incident Reporter | F287: Paras HMRI Patna | G287: Patna | H287: meenakshipandey73555@gmail.com | I287: 9151755620 | J287: PT-PAT-06087 | K287: Jibi Varghese | L287: Nursing | M287: Ward Incharge | N287: 45504
A288: 331 | B288: jesujackinlawrence | C288: Paras@123 | D288: ONCOLOGY | E288: Incident Reporter | F288: Paras HMRI Patna | G288: Patna | H288: jackingjesu@gmail.com | I288: 6384669063 | J288: PT-PAT-06088 | K288: Manish Kumar | L288: Paramedics | M288: Sr. Manager | N288: 45505
... A559: 613 | B559: ramlisastiya | C559: Paras@123 | D559: MEDICAL SERVICES | E559: Incident Reporter | F559: Paras HMRI Patna | G559: Patna | H559: ramlisastiya21@gmail.com | I559: 7691920490 | J559: PT-PAT-06837 | K559: Anima Balbandi | L559: Nursing | M559: Staff Nurse | N559: 45953
A560: 614 | B560: harshitanand | C560: Paras@123 | D560: GENERAL & ADMINISTRTIVE SERVICES | E560: Incident Reporter | F560: Paras HMRI Patna | G560: Patna | I560: 9006455422 | J560: PT-PAT-06842 | K560: Ramavtar Jangid | L560: Administration | M560: Executive- Level 1 | N560: 45960
A561: 615 | B561: ananditanamitamundu | C561: Paras@123 | D561: MEDICAL SERVICES | E561: Incident Reporter | F561: Paras HMRI Patna | G561: Patna | H561: ananditanamita@gmail.com | I561: 8340749531 | J561: PT-PAT-06845 | K561: Jibi Varghese | L561: Nursing | M561: Sr. Staff Nurse | N561: 45964
A562: 616 | B562: samarjeet | C562: Paras@123 | D562: SUPPLY CHAIN MANAGEMENT | E562: Incident Reporter | F562: Paras HMRI Patna | G562: Patna | I562: 8826362517 | J562: PT-PAT-06850 | K562: Vikrant Singh | L562: Administration | M562: Sr. Executive- Level 1 | N562: 45965
A563: 617 | B563: ratnanjali | C563: Paras@123 | D563: CARDIOLOGY | E563: Incident Reporter | F563: Paras HMRI Patna | G563: Patna | I563: 8303517880 | J563: PT-PAT-06851 | K563: Manish Kumar | L563: Paramedics | M563: Technician - Level 1 | N563: 45967
A564: 618 | B564: rituraj | C564: Paras@123 | D564: Dialysis | E564: Incident Reporter | F564: Paras HMRI Patna | G564: Patna | I564: 7759904856 | J564: PT-PAT-06853 | K564: Dalip Kumar | L564: Paramedics | M564: Sr. Technician - Level 1 | N564: 45968
A565: 619 | B565: rambabukumar | C565: Paras@123 | D565: Admissions | E565: Incident Reporter | F565: Paras HMRI Patna | G565: Patna | I565: 7654663749 | J565: PT-PAT-06857 | K565: Ramavtar Jangid | L565: Support | M565: Coordinator- Level 1 | N565: 45971
A566: 620 | B566: anjalikumari | C566: Paras@123 | D566: MEDICAL SERVICES | E566: Incident Reporter | F566: Paras HMRI Patna | G566: Patna | I566: 6204251774 | J566: PT-PAT-06858 | K566: Anima Balbandi | L566: Nursing | M566: Staff Nurse | N566: 45971
A567: 621 | B567: aarti | C567: Paras@123 | D567: BILLING | E567: Incident Reporter | F567: Paras HMRI Patna | G567: Patna | I567: 8802400136 | J567: PT-PAT-06859 | K567: Ramavtar Jangid | L567: Support | M567: Executive- Level 1 | N567: 45971
A568: 622 | B568: kalanikumari | C568: Paras@123 | D568: Respiratory ICU | E568: Incident Reporter | F568: Paras HMRI Patna | G568: Patna | I568: 9523229781 | J568: PT-PAT-06860 | K568: Neha Mehta | L568: Nursing | M568: Staff Nurse | N568: 45971
A569: 623 | B569: salimahmadansari | C569: Paras@123 | D569: OT | E569: Incident Reporter | F569: Paras HMRI Patna | G569: Patna | I569: 8969867728 | J569: PT-PAT-06863 | K569: Manisha Kumari | L569: Nursing | M569: Staff Nurse | N569: 45972
A570: 624 | B570: simranmuskan | C570: Paras@123 | D570: BILLING | E570: Incident Reporter | F570: Paras HMRI Patna | G570: Patna | I570: 8102228393 | J570: PT-PAT-06864 | K570: Ramavtar Jangid | L570: Support | M570: Executive- Level 1 | N570: 45973
A571: 625 | B571: muskankumari | C571: Paras@123 | D571: GENERAL & ADMINISTRTIVE SERVICES | E571: Incident Reporter | F571: Paras HMRI Patna | G571: Patna | I571: 6203828120 | J571: PT-PAT-06865 | K571: Ramavtar Jangid | L571: Administration | M571: Executive- Level 1 | N571: 45973
A572: 626 | B572: ankitkumar | C572: Paras@123 | D572: Camp Services | E572: Incident Reporter | F572: Paras HMRI Patna | G572: Patna | I572: 6204799745 | J572: PT-PAT-06867 | K572: Rohit Kumar | L572: Administration | M572: Executive- Level 1 | N572: 45973
A573: 627 | B573: rupamehata | C573: Paras@123 | D573: MEDICAL SERVICES | E573: Incident Reporter | F573: Paras HMRI Patna | G573: Patna | I573: 8789218840 | J573: PT-PAT-06868 | K573: Minakshi Pandey | L573: Nursing | M573: Staff Nurse | N573: 45974
A574: 628 | B574: pankajkumar | C574: Paras@123 | D574: BILLING | E574: Incident Reporter | F574: Paras HMRI Patna | G574: Patna | H574: pankajkumarm930@gmail.com | I574: 8002665369 | J574: PT-PAT-06869 | K574: Ramavtar Jangid | L574: Support | M574: Executive- Level 1 | N574: 45974
A575: 629 | B575: kartavyarai | C575: Paras@123 | D575: MEDICAL RECORD DEPARTMENT | E575: Incident Reporter | F575: Paras HMRI Patna | G575: Patna | I575: 9341117920 | J575: PT-PAT-06871 | K575: Harendra Kumar Divakar | L575: Administration | M575: Executive- Level 1 | N575: 45974
A576: 630 | B576: ankitkumaryadav | C576: Paras@123 | D576: Dialysis | E576: Incident Reporter | F576: Paras HMRI Patna | G576: Patna | I576: 8210680967 | J576: PT-PAT-06872 | K576: Dalip Kumar | L576: Paramedics | M576: Technician - Level 1 | N576: 45974
A577: 631 | B577: manisharanjan | C577: Paras@123 | D577: OT | E577: Incident Reporter | F577: Paras HMRI Patna | G577: Patna | I577: 7273962254 | J577: PT-PAT-06873 | K577: Neha Singh | L577: Nursing | M577: Staff Nurse | N577: 45975
A578: 632 | B578: adityakumar | C578: Paras@123 | D578: OT | E578: Incident Reporter | F578: Paras HMRI Patna | G578: Patna | I578: 7033124840 | J578: PT-PAT-06874 | K578: Manisha Kumari | L578: Nursing | M578: Staff Nurse | N578: 45975
A579: 633 | B579: zakeerhussain | C579: Paras@123 | D579: MEDICAL SERVICES | E579: Incident Reporter | F579: Paras HMRI Patna | G579: Patna | I579: 7091292657 | J579: PT-PAT-06875 | K579: Rinku Kumari | L579: Nursing | M579: Staff Nurse | N579: 45976
A580: 634 | B580: stutikumari | C580: Paras@123 | D580: NEUROLOGY | E580: Incident Reporter | F580: Paras HMRI Patna | G580: Patna | H580: stutikumari090@gmail.com | I580: 7762860341 | J580: PT-PAT-06876 | K580: Tannya Yadav | L580: Nursing | M580: Staff Nurse | N580: 45978
A581: 635 | B581: shashikantsharma | C581: Paras@123 | D581: INFORMATION TECHNOLOGY | E581: Incident Reporter | F581: Paras HMRI Patna | G581: Patna | I581: 9852720608 | J581: PT-PAT-06878 | K581: Krishna Kumar | L581: Support | M581: Sr. Executive- Level 1 | N581: 45978
A582: 636 | B582: santoshkumar | C582: Paras@123 | D582: CARDIOLOGY | E582: Incident Reporter | F582: Paras HMRI Patna | G582: Patna | I582: 9136743734 | J582: PT-PAT-06879 | K582: Chandan Kumar | L582: Revenue Generating Doctors | M582: Attending Consultant | N582: 45978
A583: 637 | B583: mdqamarraza | C583: Paras@123 | D583: MEDICAL SERVICES | E583: Incident Reporter | F583: Paras HMRI Patna | G583: Patna | I583: 7519527786 | J583: PT-PAT-06880 | K583: Punam Soren | L583: Nursing | M583: Staff Nurse | N583: 45978
A584: 638 | B584: rajeevranjan | C584: Paras@123 | D584: BILLING | E584: Incident Reporter | F584: Paras HMRI Patna | G584: Patna | I584: 6201729545 | J584: PT-PAT-06881 | K584: Harendra Kumar Singh | L584: Administration | M584: Sr. Executive- Level 1 | N584: 45978
A585: 639 | B585: mdasifiqbal | C585: Paras@123 | D585: BILLING | E585: Incident Reporter | F585: Paras HMRI Patna | G585: Patna | I585: 9113149793 | J585: PT-PAT-06882 | K585: Harendra Kumar Singh | L585: Administration | M585: Sr. Executive- Level 1 | N585: 45978
A586: 640 | B586: sahbealam | C586: Paras@123 | D586: Respiratory ICU | E586: Incident Reporter | F586: Paras HMRI Patna | G586: Patna | I586: 7091697050 | J586: PT-PAT-06883 | K586: Neha Mehta | L586: Nursing | M586: Staff Nurse | N586: 45978
A587: 641 | B587: rajeevkumar | C587: Paras@123 | D587: BILLING | E587: Incident Reporter | F587: Paras HMRI Patna | G587: Patna | I587: 9570873872 | J587: PT-PAT-06884 | K587: Ramavtar Jangid | L587: Support | M587: Executive- Level 1 | N587: 45978
A588: 642 | B588: deepakkumar | C588: Paras@123 | D588: EMERGENCY | E588: Incident Reporter | F588: Paras HMRI Patna | G588: Patna | I588: 7644075615 | J588: PT-PAT-06886 | K588: Onkar Mani Tirpathi | L588: Nursing | M588: Staff Nurse | N588: 45979
A589: 643 | B589: himanshuray | C589: Paras@123 | D589: MEDICAL SERVICES | E589: Incident Reporter | F589: Paras HMRI Patna | G589: Patna | H589: himanshu672614@gmail.com | I589: 6201724963 | J589: PT-PAT-06887 | K589: Anandita Namita Mundu | L589: Nursing | M589: Staff Nurse | N589: 45979
A590: 644 | B590: soumyaprakash | C590: Paras@123 | D590: GENERAL & ADMINISTRTIVE SERVICES | E590: Incident Reporter | F590: Paras HMRI Patna | G590: Patna | H590: drsoumya.prakash@parashospitals.com | I590: 9044978581 | J590: PT-PAT-06890 | K590: Manish Kumar | L590: Administration | M590: Assistant Manager | N590: 45981
A591: 645 | B591: shammaanjum | C591: Paras@123 | D591: CARDIOLOGY | E591: Incident Reporter | F591: Paras HMRI Patna | G591: Patna | H591: shamaanjum949@gmail.com | I591: 7050842152 | J591: PT-PAT-06894 | K591: Archana Chandra | L591: Nursing | M591: Staff Nurse | N591: 45981
A592: 646 | B592: sonukumar | C592: Paras@123 | D592: Pharmacy | E592: Incident Reporter | F592: Paras HMRI Patna | G592: Patna | I592: 7541047066 | J592: PT-PAT-06895 | K592: Arbind Prasad | L592: Paramedics | M592: Sr. Pharmacist - Level 1 | N592: 45981
A593: 647 | B593: deepankarjangid | C593: Paras@123 | D593: GUEST RELATIONS | E593: Incident Reporter | F593: Paras HMRI Patna | G593: Patna | I593: 9783825459 | J593: PT-PAT-06897 | K593: Ramavtar Jangid | L593: Support | M593: Assistant Manager | N593: 45982
A594: 648 | B594: monukumar | C594: Paras@123 | D594: MEDICAL SERVICES | E594: Incident Reporter | F594: Paras HMRI Patna | G594: Patna | I594: 6203241483 | J594: PT-PAT-06898 | K594: Soni Paswan | L594: Nursing | M594: Sr. Staff Nurse | N594: 45982
A595: 649 | B595: deepshikhabhave | C595: Paras@123 | D595: ONCOLOGY | E595: Incident Reporter | F595: Paras HMRI Patna | G595: Patna | I595: 9673783487 | J595: PT-PAT-06899 | K595: Manish Kumar | L595: Doctors | M595: Resident Medical Officer | N595: 45976
A596: 650 | B596: punamkumari | C596: Paras@123 | D596: MEDICAL SERVICES | E596: Incident Reporter | F596: Paras HMRI Patna | G596: Patna | I596: 8521382944 | J596: PT-PAT-06900 | K596: Minakshi Pandey | L596: Nursing | M596: Staff Nurse | N596: 45982
A597: 651 | B597: ravikumar | C597: Paras@123 | D597: OT | E597: Incident Reporter | F597: Paras HMRI Patna | G597: Patna | I597: 8210073237 | J597: PT-PAT-06901 | K597: Neha Singh | L597: Paramedics | M597: Technician - Level 1 | N597: 45982
A598: 652 | B598: bholamandal | C598: Paras@123 | D598: MEDICAL SERVICES | E598: Incident Reporter | F598: Paras HMRI Patna | G598: Patna | I598: 9334525948 | J598: PT-PAT-06902 | K598: Punam Soren | L598: Nursing | M598: Staff Nurse | N598: 45982
A599: 653 | B599: priyankakumari | C599: Paras@123 | D599: MEDICAL SERVICES | E599: Incident Reporter | F599: Paras HMRI Patna | G599: Patna | I599: 7633897574 | J599: PT-PAT-06903 | K599: KM Priti Bharti | L599: Nursing | M599: Staff Nurse | N599: 45982
A600: 654 | B600: sanketkumar | C600: Paras@123 | D600: INTERNAL MEDICINE | E600: Incident Reporter | F600: Paras HMRI Patna | G600: Patna | I600: 9804926232 | J600: PT-PAT-06904 | K600: Sudhakar Mishra | L600: Doctors | M600: Senior Medical Officer | N600: 45985
A601: 655 | B601: shivanikumari | C601: Paras@123 | D601: BILLING | E601: Incident Reporter | F601: Paras HMRI Patna | G601: Patna | I601: 7204339055 | J601: PT-PAT-06905 | K601: Harendra Kumar Singh | L601: Administration | M601: Executive- Level 1 | N601: 45985
A602: 656 | B602: mdgulzaralam | C602: Paras@123 | D602: MEDICAL SERVICES | E602: Incident Reporter | F602: Paras HMRI Patna | G602: Patna | I602: 9661321722 | J602: PT-PAT-06906 | K602: KM Priti Bharti | L602: Nursing | M602: Staff Nurse | N602: 45985
A603: 657 | B603: ayushkumarsingh | C603: Paras@123 | D603: MEDICAL SERVICES | E603: Incident Reporter | F603: Paras HMRI Patna | G603: Patna | I603: 8009204768 | J603: PT-PAT-06907 | K603: Anandita Namita Mundu | L603: Nursing | M603: Staff Nurse | N603: 45985
... A653: 710 | B653: mrityunjaykumar | C653: Paras@123 | D653: INTERNAL MEDICINE | E653: Incident Reporter | F653: Paras HMRI Patna | G653: Patna | I653: 7011706070 | J653: PT-PAT-06979 | K653: Anil Kumar | L653: Revenue Generating Doctors | M653: Director | N653: 46027
A654: 711 | B654: manishkumar | C654: Paras@123 | D654: SALES & MARKETING | E654: Incident Reporter | F654: Paras HMRI Patna | G654: Patna | H654: manish.kumar1@parashealth.com | I654: 9827103232 | J654: PT-PAT-06980 | K654: Rohit Kumar | L654: Administration | M654: Assistant Manager | N654: 46027
A655: 712 | B655: preetikumari | C655: Paras@123 | D655: DISPATCH CENTER | E655: Incident Reporter | F655: Paras HMRI Patna | G655: Patna | I655: 7301955408 | J655: PT-PAT-06981 | K655: Shailesh Mauar | L655: Administration | M655: Sr. Executive- Level 1 | N655: 46027
A656: 713 | B656: rajveersaran | C656: Paras@123 | D656: BILLING | E656: Incident Reporter | F656: Paras HMRI Patna | G656: Patna | I656: 9576963869 | J656: PT-PAT-06982 | K656: Ramavtar Jangid | L656: Support | M656: Executive- Level 1 | N656: 46027
A657: 714 | B657: animabalbandi | C657: Paras@123 | D657: MEDICAL SERVICES | E657: Incident Reporter | F657: Paras HMRI Patna | G657: Patna | I657: 8252383073 | J657: PT-PAT-06983 | K657: Jibi Varghese | L657: Nursing | M657: Ward Incharge | N657: 46027
A658: 715 | B658: nishakumari | C658: Paras@123 | D658: MICU | E658: Incident Reporter | F658: Paras HMRI Patna | G658: Patna | I658: 9135101903 | J658: PT-PAT-06984 | K658: Reena Kumari | L658: Nursing | M658: Staff Nurse | N658: 46027
A659: 716 | B659: komalkumari | C659: Paras@123 | D659: MEDICAL SERVICES | E659: Incident Reporter | F659: Paras HMRI Patna | G659: Patna | I659: 7479885762 | J659: PT-PAT-06986 | K659: KM Priti Bharti | L659: Nursing | M659: Staff Nurse | N659: 46027
A660: 717 | B660: rohitkumar | C660: Paras@123 | D660: SALES & MARKETING | E660: Incident Reporter | F660: Paras HMRI Patna | G660: Patna | I660: 7759855272 | J660: PT-PAT-06987 | K660: Anil Kumar | L660: Administration | M660: Senior General Manager | N660: 46028
A661: 718 | B661: trishnachatterjee | C661: Paras@123 | D661: GENERAL & ADMINISTRTIVE SERVICES | E661: Incident Reporter | F661: Paras HMRI Patna | G661: Patna | I661: 8918763221 | J661: PT-PAT-06988 | K661: Md Shariful Haque | L661: Administration | M661: Executive- Level 1 | N661: 46028
A662: 719 | B662: syedzulfequarashraf | C662: Paras@123 | D662: MEDICAL SERVICES | E662: Incident Reporter | F662: Paras HMRI Patna | G662: Patna | I662: 7050202180 | J662: PT-PAT-06989 | K662: Soni Paswan | L662: Nursing | M662: Staff Nurse | N662: 46028
A663: 720 | B663: sonamkumari | C663: Paras@123 | D663: CARDIOLOGY | E663: Incident Reporter | F663: Paras HMRI Patna | G663: Patna | I663: 8210500740 | J663: PT-PAT-06990 | K663: Manish Kumar | L663: Paramedics | M663: Technician - Level 1 | N663: 46028
A664: 721 | B664: nehasingh | C664: Paras@123 | D664: OT | E664: Incident Reporter | F664: Paras HMRI Patna | G664: Patna | I664: 9162854831 | J664: PT-PAT-06991 | K664: Manish Kumar | L664: Paramedics | M664: Manager | N664: 46030
A665: 722 | B665: taufiqehsan | C665: Paras@123 | D665: CSSD | E665: Incident Reporter | F665: Paras HMRI Patna | G665: Patna | I665: 8235891264 | J665: PT-PAT-06992 | K665: Atishay Ranjan | L665: Paramedics | M665: Technician - Level 1 | N665: 46034
A666: 723 | B666: jyoti | C666: Paras@123 | D666: GUEST RELATIONS | E666: Incident Reporter | F666: Paras HMRI Patna | G666: Patna | I666: 8882593259 | J666: PT-PAT-06993 | K666: Ramavtar Jangid | L666: Support | M666: Executive- Level 1 | N666: 46034
...

Sheet Sheet8
E1: Academics | F1: ACADEMICS RESEARCH | K1: ACADEMICS RESEARCH
E2: Accounts | F2: FINANCE & ACCOUNTS | K2: Admissions
E3: Administration | F3: GENERAL & ADMINISTRTIVE SERVICES | K3: ALTERNATIVE MEDICINE
E4: Admission | F4: Admissions | K4: AMBULATORY SERVICES
E5: Arthroscopy | F5: Arthroscopy | K5: ANESTHESIOLOGY
E6: Billing | F6: BILLING | K6: BARIATRIC AND METABOLIC SURGERY
E7: Bio Chemistry | F7: Biochemistry | K7: BILLING
E8: Biomedical Engineering | F8: BIOMEDICAL ENGINEERING | K8: Biochemistry
E9: Blood Bank | F9: BLOOD BANK | K9: BIOMEDICAL ENGINEERING
E10: Branding | F10: SALES & MARKETING | K10: BLOOD BANK
E11: Call Centre | F11: CALL CENTRE | K11: BMT
E12: Camp Services | F12: Camp Services | K12: CALL CENTRE
... E114: Urology | F114: UROLOGY | K114: Pharmacy
K115: PHYSIOTHERAPY
K116: PLASTIC SURGERY
K117: PROJECTS
K118: PSYCHIATRY
K119: PSYCHOTHERAPY
K120: Pulmonary Lab
K121: Pulmonology
K122: QUALITY
K123: RADIOLOGY
K124: RESPIRATORY MEDICINE
K125: RHEUMATOLOGY AND CLINICAL IMMUNOLOGY
K126: Round Off
... K138: Vascular Surgery
